<xigt-corpus xmlns:dc="http://purl.org/dc/elements/1.1/" xmlns:olac="http://www.language-archives.org/OLAC/1.1/" xmlns:xsi="http://www.w3.org/2001/XMLSchema-instance">
  <igt id="igt1403-25" doc-id="1403" line-range="379-381" tag-types="L+LN G T">
    <metadata>
      <meta id="meta1">
        <dc:subject olac:code="sat" xsi:type="olac:language">Santali</dc:subject>
        <dc:language olac:code="en" xsi:type="olac:language">English</dc:language>
      </meta>
    </metadata>
    <tier id="r" type="odin" state="raw">
      <item id="r1" line="379" tag="L+LN">         b.     uni dal -oco -m -a -e                                                 Santali</item>
      <item id="r2" line="380" tag="G">                he beat-caus-2sO- FIN-3sS</item>
      <item id="r3" line="381" tag="T">                `he makes you beat'</item>
    </tier>
    <tier id="c" type="odin" alignment="r" state="cleaned">
      <item id="c1" alignment="r1" line="379" tag="L+LN">b.     uni dal -oco -m -a -e                                                 Santali</item>
      <item id="c2" alignment="r2" line="380" tag="G">       he beat-caus-2sO- FIN-3sS</item>
      <item id="c3" alignment="r3" line="381" tag="T">       `he makes you beat'</item>
    </tier>
    <tier id="n" type="odin" alignment="c" state="normalized">
      <item id="n1" alignment="c1" line="379" tag="L">uni dal-oco-m-a-e</item>
      <item id="n2" alignment="c2" line="380" tag="G">he beat-caus-2sO-FIN-3sS</item>
      <item id="n3" alignment="c3" line="381" tag="T">he makes you beat</item>
      <item id="n4" alignment="c1" line="379" tag="M+LN">Santali</item>
    </tier>
  </igt>
  <igt id="igt2628-42" doc-id="2628" line-range="415-417" tag-types="L G T">
    <metadata>
      <meta id="meta1">
        <dc:subject olac:code="sat" xsi:type="olac:language">Santali</dc:subject>
        <dc:language olac:code="en" xsi:type="olac:language">English</dc:language>
      </meta>
    </metadata>
    <tier id="r" type="odin" state="raw">
      <item id="r1" line="415" tag="L">       a.     ba-ko     badae-a</item>
      <item id="r2" line="416" tag="G">              NEG-3P know-IND</item>
      <item id="r3" line="417" tag="T">              `they don't know'</item>
    </tier>
    <tier id="c" type="odin" alignment="r" state="cleaned">
      <item id="c1" alignment="r1" line="415" tag="L">a.     ba-ko     badae-a</item>
      <item id="c2" alignment="r2" line="416" tag="G">       NEG-3P know-IND</item>
      <item id="c3" alignment="r3" line="417" tag="T">       `they don't know'</item>
    </tier>
    <tier id="n" type="odin" alignment="c" state="normalized">
      <item id="n1" alignment="c1" line="415" tag="L">ba-ko     badae-a</item>
      <item id="n2" alignment="c2" line="416" tag="G">NEG-3P know-IND</item>
      <item id="n3" alignment="c3" line="417" tag="T">they don't know</item>
    </tier>
  </igt>
  <igt id="igt2628-43" doc-id="2628" line-range="419-422" tag-types="L+CR L+CR G T">
    <metadata>
      <meta id="meta1">
        <dc:subject olac:code="sat" xsi:type="olac:language">Santali</dc:subject>
        <dc:language olac:code="en" xsi:type="olac:language">English</dc:language>
      </meta>
    </metadata>
    <tier id="r" type="odin" state="raw">
      <item id="r1" line="419" tag="L+CR">              met-a-pe-kan-a-</item>
      <item id="r2" line="420" tag="L+CR">       b.</item>
      <item id="r3" line="421" tag="G">              say-APPL-2SO-IPFV-IND-1S</item>
      <item id="r4" line="422" tag="T">              `I tell you'</item>
    </tier>
    <tier id="c" type="odin" alignment="r" state="cleaned">
      <item id="c1" alignment="r1" line="419 420" tag="L">b.     met-a-pe-kan-a-</item>
      <item id="c2" alignment="r3" line="421" tag="G">       say-APPL-2SO-IPFV-IND-1S</item>
      <item id="c3" alignment="r4" line="422" tag="T">       `I tell you'</item>
    </tier>
    <tier id="n" type="odin" alignment="c" state="normalized">
      <item id="n1" alignment="c1" line="419 420" tag="L">met-a-pe-kan-a-</item>
      <item id="n2" alignment="c2" line="421" tag="G">say-APPL-2SO-IPFV-IND-1S</item>
      <item id="n3" alignment="c3" line="422" tag="T">I tell you</item>
    </tier>
  </igt>
  <igt id="igt2628-44" doc-id="2628" line-range="424-427" tag-types="L+CR L+CR G T">
    <metadata>
      <meta id="meta1">
        <dc:subject olac:code="sat" xsi:type="olac:language">Santali</dc:subject>
        <dc:language olac:code="en" xsi:type="olac:language">English</dc:language>
      </meta>
    </metadata>
    <tier id="r" type="odin" state="raw">
      <item id="r1" line="424" tag="L+CR">              mas       mit' ghri      dh-g-e-pe!</item>
      <item id="r2" line="425" tag="L+CR">       c.</item>
      <item id="r3" line="426" tag="G">              PTCL      one   moment put down-litle-1SO-2P</item>
      <item id="r4" line="427" tag="T">              `put me down for a moment'</item>
    </tier>
    <tier id="c" type="odin" alignment="r" state="cleaned">
      <item id="c1" alignment="r1" line="424 425" tag="L">c.     mas       mit' ghri      dh-g-e-pe!</item>
      <item id="c2" alignment="r3" line="426" tag="G">       PTCL      one   moment put down-litle-1SO-2P</item>
      <item id="c3" alignment="r4" line="427" tag="T">       `put me down for a moment'</item>
    </tier>
    <tier id="n" type="odin" alignment="c" state="normalized">
      <item id="n1" alignment="c1" line="424 425" tag="L">mas       mit' ghri      dh-g-e-pe!</item>
      <item id="n2" alignment="c2" line="426" tag="G">PTCL      one   moment put down-litle-1SO-2P</item>
      <item id="n3" alignment="c3" line="427" tag="T">put me down for a moment</item>
    </tier>
  </igt>
  <igt id="igt2733-34" doc-id="2733" line-range="451-453" tag-types="L G T">
    <metadata>
      <meta id="meta1">
        <dc:subject olac:code="sat" xsi:type="olac:language">Santali</dc:subject>
        <dc:language olac:code="en" xsi:type="olac:language">English</dc:language>
      </meta>
    </metadata>
    <tier id="r" type="odin" state="raw">
      <item id="r1" line="451" tag="L">        a.     ba-ko       badae-a</item>
      <item id="r2" line="452" tag="G">               NEG-3P know-IND</item>
      <item id="r3" line="453" tag="T">               `they don't know'</item>
    </tier>
    <tier id="c" type="odin" alignment="r" state="cleaned">
      <item id="c1" alignment="r1" line="451" tag="L">a.     ba-ko       badae-a</item>
      <item id="c2" alignment="r2" line="452" tag="G">       NEG-3P know-IND</item>
      <item id="c3" alignment="r3" line="453" tag="T">       `they don't know'</item>
    </tier>
    <tier id="n" type="odin" alignment="c" state="normalized">
      <item id="n1" alignment="c1" line="451" tag="L">ba-ko       badae-a</item>
      <item id="n2" alignment="c2" line="452" tag="G">NEG-3P know-IND</item>
      <item id="n3" alignment="c3" line="453" tag="T">they don't know</item>
    </tier>
  </igt>
  <igt id="igt2733-35" doc-id="2733" line-range="454-457" tag-types="L+CR L+CR G T">
    <metadata>
      <meta id="meta1">
        <dc:subject olac:code="sat" xsi:type="olac:language">Santali</dc:subject>
        <dc:language olac:code="en" xsi:type="olac:language">English</dc:language>
      </meta>
    </metadata>
    <tier id="r" type="odin" state="raw">
      <item id="r1" line="454" tag="L+CR">               met-a-pe-kan-a-¯</item>
      <item id="r2" line="455" tag="L+CR">        b.</item>
      <item id="r3" line="456" tag="G">               say-APPL-2SO-IPFV-IND-1S</item>
      <item id="r4" line="457" tag="T">               `I tell you'</item>
    </tier>
    <tier id="c" type="odin" alignment="r" state="cleaned">
      <item id="c1" alignment="r1" line="454 455" tag="L">b.     met-a-pe-kan-a-¯</item>
      <item id="c2" alignment="r3" line="456" tag="G">       say-APPL-2SO-IPFV-IND-1S</item>
      <item id="c3" alignment="r4" line="457" tag="T">       `I tell you'</item>
    </tier>
    <tier id="n" type="odin" alignment="c" state="normalized">
      <item id="n1" alignment="c1" line="454 455" tag="L">met-a-pe-kan-a-¯</item>
      <item id="n2" alignment="c2" line="456" tag="G">say-APPL-2SO-IPFV-IND-1S</item>
      <item id="n3" alignment="c3" line="457" tag="T">I tell you</item>
    </tier>
  </igt>
  <igt id="igt2733-36" doc-id="2733" line-range="458-461" tag-types="L+CR L+CR G T">
    <metadata>
      <meta id="meta1">
        <dc:subject olac:code="sat" xsi:type="olac:language">Santali</dc:subject>
        <dc:language olac:code="en" xsi:type="olac:language">English</dc:language>
      </meta>
    </metadata>
    <tier id="r" type="odin" state="raw">
      <item id="r1" line="458" tag="L+CR">               masE        mit' ghÇri   dçhç-¯ç,g-e¯-pe!</item>
      <item id="r2" line="459" tag="L+CR">        c.</item>
      <item id="r3" line="460" tag="G">               PTCL        one   moment put down-litle-1SO-2P</item>
      <item id="r4" line="461" tag="T">               `put me down for a moment'</item>
    </tier>
    <tier id="c" type="odin" alignment="r" state="cleaned">
      <item id="c1" alignment="r1" line="458 459" tag="L">c.     masE        mit' ghÇri   dçhç-¯ç,g-e¯-pe!</item>
      <item id="c2" alignment="r3" line="460" tag="G">       PTCL        one   moment put down-litle-1SO-2P</item>
      <item id="c3" alignment="r4" line="461" tag="T">       `put me down for a moment'</item>
    </tier>
    <tier id="n" type="odin" alignment="c" state="normalized">
      <item id="n1" alignment="c1" line="458 459" tag="L">masE        mit' ghÇri   dçhç-¯ç,g-e¯-pe!</item>
      <item id="n2" alignment="c2" line="460" tag="G">PTCL        one   moment put down-litle-1SO-2P</item>
      <item id="n3" alignment="c3" line="461" tag="T">put me down for a moment</item>
    </tier>
  </igt>
</xigt-corpus>
