<xigt-corpus xmlns:dc="http://purl.org/dc/elements/1.1/" xmlns:olac="http://www.language-archives.org/OLAC/1.1/" xmlns:xsi="http://www.w3.org/2001/XMLSchema-instance">
  <igt id="igt3315-1" doc-id="3315" line-range="32-36" tag-types="L+DB+CR L+DB+CR G+DB T+DB T+DB+AL">
    <metadata>
      <meta id="meta1">
        <dc:subject olac:code="srp:hrv" xsi:type="olac:language">Serbocroatian</dc:subject>
        <dc:language olac:code="en" xsi:type="olac:language">English</dc:language>
      </meta>
    </metadata>
    <tier id="r" type="odin" state="raw">
      <item id="r1" line="32" tag="L+DB+CR">                 c.        Poljubio           sam Sofiju.     d.   Ju er       sam poljubio                          Sofiju.</item>
      <item id="r2" line="33" tag="L+DB+CR">                                                                      F</item>
      <item id="r3" line="34" tag="G+DB">                           (I)kissedPf am Sofia                    yesterday am (I)kissedPf Sofia</item>
      <item id="r4" line="35" tag="T+DB">                           a) I kissed Sofia.                      a) I kissed Sofia yesterday.</item>
      <item id="r5" line="36" tag="T+DB+AL">                           b) I have kissed Sofia.                 b) *I have kissed Sofia yesterday.</item>
    </tier>
    <tier id="c" type="odin" alignment="r" state="cleaned">
      <item id="c1" alignment="r1" line="32" tag="L+DB+CR">c.        Poljubio           sam Sofiju.     d.   Ju er       sam poljubio                          Sofiju.</item>
      <item id="c2" alignment="r3" line="34" tag="G+DB">          (I)kissedPf am Sofia                    yesterday am (I)kissedPf Sofia</item>
      <item id="c3" alignment="r4" line="35" tag="T+DB">          a) I kissed Sofia.                      a) I kissed Sofia yesterday.</item>
      <item id="c4" alignment="r5" line="36" tag="T+DB+AL">          b) I have kissed Sofia.                 b) *I have kissed Sofia yesterday.</item>
    </tier>
    <tier id="n" type="odin" alignment="c" state="normalized">
      <item id="n1" alignment="c1" line="32" tag="L+DB+CR">Poljubio           sam Sofiju.     d.   Ju er       sam poljubio                          Sofiju.</item>
      <item id="n2" alignment="c2" line="34" tag="G+DB">(I)kissedPf am Sofia                    yesterday am (I)kissedPf Sofia</item>
      <item id="n3" alignment="c3" line="35" tag="T+DB">a) I kissed Sofia.                      a) I kissed Sofia yesterday.</item>
      <item id="n4" alignment="c4" line="36" tag="T+DB+AL">b) I have kissed Sofia.                 b) *I have kissed Sofia yesterday.</item>
    </tier>
  </igt>
  <igt id="igt3315-2" doc-id="3315" line-range="153-154" tag-types="M+CN+DB L-T+DB">
    <metadata>
      <meta id="meta1">
        <dc:subject olac:code="srp:hrv" xsi:type="olac:language">Serbocroatian</dc:subject>
        <dc:language olac:code="en" xsi:type="olac:language">English</dc:language>
      </meta>
    </metadata>
    <tier id="r" type="odin" state="raw">
      <item id="r1" line="153" tag="M+CN+DB">  2)                 a.              imperfective                                perfective</item>
      <item id="r2" line="154" tag="L-T+DB">                                     pisati    `write Inf'                       napisati            `write up Inf'</item>
    </tier>
    <tier id="c" type="odin" alignment="r" state="cleaned">
      <item id="c1" alignment="r1" line="153" tag="M+CN+DB">2)                 a.              imperfective                                perfective</item>
      <item id="c2" alignment="r2" line="154" tag="L-T+DB">pisati    `write Inf'                       napisati            `write up Inf'</item>
    </tier>
    <tier id="n" type="odin" alignment="c" state="normalized">
      <item id="n1" alignment="c1" line="153" tag="M+CN+DB">2)                 a.              imperfective                                perfective</item>
      <item id="n2" alignment="c2" line="154" tag="L-T+DB">pisati    `write Inf'                       napisati            `write up Inf'</item>
    </tier>
  </igt>
  <igt id="igt3315-3" doc-id="3315" line-range="155-155" tag-types="L-T+DB">
    <metadata>
      <meta id="meta1">
        <dc:subject olac:code="srp:hrv" xsi:type="olac:language">Serbocroatian</dc:subject>
        <dc:language olac:code="en" xsi:type="olac:language">English</dc:language>
      </meta>
    </metadata>
    <tier id="r" type="odin" state="raw">
      <item id="r1" line="155" tag="L-T+DB">                                     pjevati   `sing Inf'                        otpjevati           `finish singing'</item>
    </tier>
    <tier id="c" type="odin" alignment="r" state="cleaned">
      <item id="c1" alignment="r1" line="155" tag="L-T+DB">pjevati   `sing Inf'                        otpjevati           `finish singing'</item>
    </tier>
    <tier id="n" type="odin" alignment="c" state="normalized">
      <item id="n1" alignment="c1" line="155" tag="L-T+DB">pjevati   `sing Inf'                        otpjevati           `finish singing'</item>
    </tier>
  </igt>
  <igt id="igt3315-4" doc-id="3315" line-range="158-159" tag-types="M+CN+DB L-T+DB">
    <metadata>
      <meta id="meta1">
        <dc:subject olac:code="srp:hrv" xsi:type="olac:language">Serbocroatian</dc:subject>
        <dc:language olac:code="en" xsi:type="olac:language">English</dc:language>
      </meta>
    </metadata>
    <tier id="r" type="odin" state="raw">
      <item id="r1" line="158" tag="M+CN+DB">                     b.              perfective                                  imperfective</item>
      <item id="r2" line="159" tag="L-T+DB">                                     kupiti       `buy Inf'                      kupovati</item>
    </tier>
    <tier id="c" type="odin" alignment="r" state="cleaned">
      <item id="c1" alignment="r1" line="158" tag="M+CN+DB">b.              perfective                                  imperfective</item>
      <item id="c2" alignment="r2" line="159" tag="L-T+DB">kupiti       `buy Inf'                      kupovati</item>
    </tier>
    <tier id="n" type="odin" alignment="c" state="normalized">
      <item id="n1" alignment="c1" line="158" tag="M+CN+DB">b.              perfective                                  imperfective</item>
      <item id="n2" alignment="c2" line="159" tag="L-T+DB">kupiti       `buy Inf'                      kupovati</item>
    </tier>
  </igt>
  <igt id="igt3315-5" doc-id="3315" line-range="160-160" tag-types="L-T+DB">
    <metadata>
      <meta id="meta1">
        <dc:subject olac:code="srp:hrv" xsi:type="olac:language">Serbocroatian</dc:subject>
        <dc:language olac:code="en" xsi:type="olac:language">English</dc:language>
      </meta>
    </metadata>
    <tier id="r" type="odin" state="raw">
      <item id="r1" line="160" tag="L-T+DB">                                     pomo i       `help Inf'                     pomagati</item>
    </tier>
    <tier id="c" type="odin" alignment="r" state="cleaned">
      <item id="c1" alignment="r1" line="160" tag="L-T+DB">pomo i       `help Inf'                     pomagati</item>
    </tier>
    <tier id="n" type="odin" alignment="c" state="normalized">
      <item id="n1" alignment="c1" line="160" tag="L-T+DB">pomo i       `help Inf'                     pomagati</item>
    </tier>
  </igt>
  <igt id="igt3315-6" doc-id="3315" line-range="218-220" tag-types="L+CN+CR L+CR T">
    <metadata>
      <meta id="meta1">
        <dc:subject olac:code="srp:hrv" xsi:type="olac:language">Serbocroatian</dc:subject>
        <dc:language olac:code="en" xsi:type="olac:language">English</dc:language>
      </meta>
    </metadata>
    <tier id="r" type="odin" state="raw">
      <item id="r1" line="218" tag="L+CN+CR">  4)      a.        imperfective: Grci                 obi                ve eraju satima.</item>
      <item id="r2" line="219" tag="L+CR">                                                             5n 2m l            o</item>
      <item id="r3" line="220" tag="T">                                              `Greeks usually dine                        for hours.'</item>
    </tier>
    <tier id="c" type="odin" alignment="r" state="cleaned">
      <item id="c1" alignment="r1" line="218" tag="L+CN+CR">4)      a.        imperfective: Grci                 obi                ve eraju satima.</item>
      <item id="c2" alignment="r3" line="220" tag="T">                                            `Greeks usually dine                        for hours.'</item>
    </tier>
    <tier id="n" type="odin" alignment="c" state="normalized">
      <item id="n1" alignment="c1" line="218" tag="L+CN+CR">imperfective: Grci                 obi                ve eraju satima.</item>
      <item id="n2" alignment="c2" line="220" tag="T">Greeks usually dine                        for hours.</item>
    </tier>
  </igt>
  <igt id="igt3315-7" doc-id="3315" line-range="223-226" tag-types="L+CR L+CN+CR G T">
    <metadata>
      <meta id="meta1">
        <dc:subject olac:code="srp:hrv" xsi:type="olac:language">Serbocroatian</dc:subject>
        <dc:language olac:code="en" xsi:type="olac:language">English</dc:language>
      </meta>
    </metadata>
    <tier id="r" type="odin" state="raw">
      <item id="r1" line="223" tag="L+CR">                                               im                                   , nazvat</item>
      <item id="r2" line="224" tag="L+CN+CR">          b.        perfective:           p                   5w vu 2t 2r 2s 2r q              2y x           2} 7| {z</item>
      <item id="r3" line="225" tag="G">                                              as soon as (I) dine (I) call will you</item>
      <item id="r4" line="226" tag="T">                                              `As soon as I dine, I'll call you.'</item>
    </tier>
    <tier id="c" type="odin" alignment="r" state="cleaned">
      <item id="c1" alignment="r1" line="223 224" tag="L+CN">b.        perfective:           p    im             5w vu 2t 2r 2s 2r q   , nazvat   2y x           2} 7| {z</item>
      <item id="c2" alignment="r3" line="225" tag="G">                                    as soon as (I) dine (I) call will you</item>
      <item id="c3" alignment="r4" line="226" tag="T">                                    `As soon as I dine, I'll call you.'</item>
    </tier>
    <tier id="n" type="odin" alignment="c" state="normalized">
      <item id="n1" alignment="c1" line="223 224" tag="L+CN">perfective:           p    im             5w vu 2t 2r 2s 2r q   , nazvat   2y x           2} 7| {z</item>
      <item id="n2" alignment="c2" line="225" tag="G">                          as soon as (I) dine (I) call will you</item>
      <item id="n3" alignment="c3" line="226" tag="T">As soon as I dine, I'll call you.</item>
    </tier>
  </igt>
  <igt id="igt3315-8" doc-id="3315" line-range="236-238" tag-types="L+CR L+CR T">
    <metadata>
      <meta id="meta1">
        <dc:subject olac:code="srp:hrv" xsi:type="olac:language">Serbocroatian</dc:subject>
        <dc:language olac:code="en" xsi:type="olac:language">English</dc:language>
      </meta>
    </metadata>
    <tier id="r" type="odin" state="raw">
      <item id="r1" line="236" tag="L+CR">  5)      a.        Grci   obi                ve eraju za deset minuta/deset minuta</item>
      <item id="r2" line="237" tag="L+CR">                                  5 2 ~</item>
      <item id="r3" line="238" tag="T">                    `Greeks usually dine                  for ten minutes/in ten minutes.'</item>
    </tier>
    <tier id="c" type="odin" alignment="r" state="cleaned">
      <item id="c1" alignment="r1" line="236 237" tag="L">5)      a.        Grci   obi    5 2 ~       ve eraju za deset minuta/deset minuta</item>
      <item id="c2" alignment="r3" line="238" tag="T">                  `Greeks usually dine                  for ten minutes/in ten minutes.'</item>
    </tier>
    <tier id="n" type="odin" alignment="c" state="normalized">
      <item id="n1" alignment="c1" line="236 237" tag="L">Grci   obi    5 2 ~       ve eraju za deset minuta/deset minuta</item>
      <item id="n2" alignment="c2" line="238" tag="T">Greeks usually dine                  for ten minutes/in ten minutes.</item>
    </tier>
  </igt>
  <igt id="igt3315-9" doc-id="3315" line-range="247-249" tag-types="L+CR L+CR T">
    <metadata>
      <meta id="meta1">
        <dc:subject olac:code="srp:hrv" xsi:type="olac:language">Serbocroatian</dc:subject>
        <dc:language olac:code="en" xsi:type="olac:language">English</dc:language>
      </meta>
    </metadata>
    <tier id="r" type="odin" state="raw">
      <item id="r1" line="247" tag="L+CR">               b.           imperfective: Grci      obi          piju deset minuta/*za deset minuta.</item>
      <item id="r2" line="248" tag="L+CR">                                                          5 2</item>
      <item id="r3" line="249" tag="T">                                            `Greeks usually drink in ten minutes/*for ten minutes.'</item>
    </tier>
    <tier id="c" type="odin" alignment="r" state="cleaned">
      <item id="c1" alignment="r1" line="247 248" tag="L">b.           imperfective: Grci      obi   5 2    piju deset minuta/*za deset minuta.</item>
      <item id="c2" alignment="r3" line="249" tag="T">                             `Greeks usually drink in ten minutes/*for ten minutes.'</item>
    </tier>
    <tier id="n" type="odin" alignment="c" state="normalized">
      <item id="n1" alignment="c1" line="247 248" tag="L">imperfective: Grci      obi   5 2    piju deset minuta/*za deset minuta.</item>
      <item id="n2" alignment="c2" line="249" tag="T">Greeks usually drink in ten minutes/*for ten minutes.</item>
    </tier>
  </igt>
  <igt id="igt3315-10" doc-id="3315" line-range="252-254" tag-types="L+CR L+CR T">
    <metadata>
      <meta id="meta1">
        <dc:subject olac:code="srp:hrv" xsi:type="olac:language">Serbocroatian</dc:subject>
        <dc:language olac:code="en" xsi:type="olac:language">English</dc:language>
      </meta>
    </metadata>
    <tier id="r" type="odin" state="raw">
      <item id="r1" line="252" tag="L+CR">               c.           perfective:     Grci    obi          popiju za deset minuta/*deset minuta.</item>
      <item id="r2" line="253" tag="L+CR">                                                          5 2</item>
      <item id="r3" line="254" tag="T">                                            `Greeks usually drink for ten minutes/*ten minutes.'</item>
    </tier>
    <tier id="c" type="odin" alignment="r" state="cleaned">
      <item id="c1" alignment="r1" line="252 253" tag="L">c.           perfective:     Grci    obi   5 2    popiju za deset minuta/*deset minuta.</item>
      <item id="c2" alignment="r3" line="254" tag="T">                             `Greeks usually drink for ten minutes/*ten minutes.'</item>
    </tier>
    <tier id="n" type="odin" alignment="c" state="normalized">
      <item id="n1" alignment="c1" line="252 253" tag="L">perfective:     Grci    obi   5 2    popiju za deset minuta/*deset minuta.</item>
      <item id="n2" alignment="c2" line="254" tag="T">Greeks usually drink for ten minutes/*ten minutes.</item>
    </tier>
  </igt>
  <igt id="igt3315-11" doc-id="3315" line-range="270-273" tag-types="L+CR L+CR G T">
    <metadata>
      <meta id="meta1">
        <dc:subject olac:code="srp:hrv" xsi:type="olac:language">Serbocroatian</dc:subject>
        <dc:language olac:code="en" xsi:type="olac:language">English</dc:language>
      </meta>
    </metadata>
    <tier id="r" type="odin" state="raw">
      <item id="r1" line="270" tag="L+CR">  6)           Ivo je progovorio          nakon duge pauze i         nastavio govoriti                         .</item>
      <item id="r2" line="271" tag="L+CR">                                                                                             2 7 7 2    2 v</item>
      <item id="r3" line="272" tag="G">               I.     is began-to-talk after long pause and continued talk                  whole hour</item>
      <item id="r4" line="273" tag="T">               `Ivo began to talk after the long pause, and continued for the whole hour.'</item>
    </tier>
    <tier id="c" type="odin" alignment="r" state="cleaned">
      <item id="c1" alignment="r1" line="270 271" tag="L">6)           Ivo je progovorio          nakon duge pauze i         nastavio govoriti       2 7 7 2    2 v    .</item>
      <item id="c2" alignment="r3" line="272" tag="G">             I.     is began-to-talk after long pause and continued talk                  whole hour</item>
      <item id="c3" alignment="r4" line="273" tag="T">             `Ivo began to talk after the long pause, and continued for the whole hour.'</item>
    </tier>
    <tier id="n" type="odin" alignment="c" state="normalized">
      <item id="n1" alignment="c1" line="270 271" tag="L">Ivo je progovorio          nakon duge pauze i         nastavio govoriti       2 7 7 2    2 v    .</item>
      <item id="n2" alignment="c2" line="272" tag="G">I.is began-to-talk after long pause and continued talk                  whole hour</item>
      <item id="n3" alignment="c3" line="273" tag="T">Ivo began to talk after the long pause, and continued for the whole hour.</item>
    </tier>
  </igt>
  <igt id="igt3315-12" doc-id="3315" line-range="280-283" tag-types="L B G T">
    <metadata>
      <meta id="meta1">
        <dc:subject olac:code="srp:hrv" xsi:type="olac:language">Serbocroatian</dc:subject>
        <dc:language olac:code="en" xsi:type="olac:language">English</dc:language>
      </meta>
    </metadata>
    <tier id="r" type="odin" state="raw">
      <item id="r1" line="280" tag="L">  7)           Ivo je pojeo sve sendvi e.          Nista nije ostalo!</item>
      <item id="r2" line="281" tag="B" />
      <item id="r3" line="282" tag="G">               I. is eat-up all sandwiches nothing not left</item>
      <item id="r4" line="283" tag="T">               `Ivo ate up all sandwiches. Nothing left!'</item>
    </tier>
    <tier id="c" type="odin" alignment="r" state="cleaned">
      <item id="c1" alignment="r1" line="280" tag="L">7)           Ivo je pojeo sve sendvi e.          Nista nije ostalo!</item>
      <item id="c2" alignment="r3" line="282" tag="G">             I. is eat-up all sandwiches nothing not left</item>
      <item id="c3" alignment="r4" line="283" tag="T">             `Ivo ate up all sandwiches. Nothing left!'</item>
    </tier>
    <tier id="n" type="odin" alignment="c" state="normalized">
      <item id="n1" alignment="c1" line="280" tag="L">Ivo je pojeo sve sendvi e.          Nista nije ostalo!</item>
      <item id="n2" alignment="c2" line="282" tag="G">I.is eat-up all sandwiches nothing not left</item>
      <item id="n3" alignment="c3" line="283" tag="T">Ivo ate up all sandwiches. Nothing left!</item>
    </tier>
  </igt>
  <igt id="igt3315-13" doc-id="3315" line-range="301-303" tag-types="L G T">
    <metadata>
      <meta id="meta1">
        <dc:subject olac:code="srp:hrv" xsi:type="olac:language">Serbocroatian</dc:subject>
        <dc:language olac:code="en" xsi:type="olac:language">English</dc:language>
      </meta>
    </metadata>
    <tier id="r" type="odin" state="raw">
      <item id="r1" line="301" tag="L">  8)       Napokon sam nagovorila Ivu da jede meso. Vise nije vegetarijanac.</item>
      <item id="r2" line="302" tag="G">           at last   am persuade I. that eat meat more not vegetarian</item>
      <item id="r3" line="303" tag="T">           `I finally persuaded Ivo to eat meat. He's not a vegetarian any more'</item>
    </tier>
    <tier id="c" type="odin" alignment="r" state="cleaned">
      <item id="c1" alignment="r1" line="301" tag="L">8)       Napokon sam nagovorila Ivu da jede meso. Vise nije vegetarijanac.</item>
      <item id="c2" alignment="r2" line="302" tag="G">         at last   am persuade I. that eat meat more not vegetarian</item>
      <item id="c3" alignment="r3" line="303" tag="T">         `I finally persuaded Ivo to eat meat. He's not a vegetarian any more'</item>
    </tier>
    <tier id="n" type="odin" alignment="c" state="normalized">
      <item id="n1" alignment="c1" line="301" tag="L">Napokon sam nagovorila Ivu da jede meso. Vise nije vegetarijanac.</item>
      <item id="n2" alignment="c2" line="302" tag="G">at last   am persuade I.that eat meat more not vegetarian</item>
      <item id="n3" alignment="c3" line="303" tag="T">I finally persuaded Ivo to eat meat. He's not a vegetarian any more</item>
    </tier>
  </igt>
  <igt id="igt3315-14" doc-id="3315" line-range="309-311" tag-types="L G T">
    <metadata>
      <meta id="meta1">
        <dc:subject olac:code="srp:hrv" xsi:type="olac:language">Serbocroatian</dc:subject>
        <dc:language olac:code="en" xsi:type="olac:language">English</dc:language>
      </meta>
    </metadata>
    <tier id="r" type="odin" state="raw">
      <item id="r1" line="309" tag="L">  9)       Ivo je namignuo Sofiji (samo jednom).</item>
      <item id="r2" line="310" tag="G">           I. is winked     S.     only once</item>
      <item id="r3" line="311" tag="T">           `Ivo winked at Sofia (only once).'</item>
    </tier>
    <tier id="c" type="odin" alignment="r" state="cleaned">
      <item id="c1" alignment="r1" line="309" tag="L">9)       Ivo je namignuo Sofiji (samo jednom).</item>
      <item id="c2" alignment="r2" line="310" tag="G">         I. is winked     S.     only once</item>
      <item id="c3" alignment="r3" line="311" tag="T">         `Ivo winked at Sofia (only once).'</item>
    </tier>
    <tier id="n" type="odin" alignment="c" state="normalized">
      <item id="n1" alignment="c1" line="309" tag="L">Ivo je namignuo Sofiji (samo jednom).</item>
      <item id="n2" alignment="c2" line="310" tag="G">I.is winked     S.only once</item>
      <item id="n3" alignment="c3" line="311" tag="T">Ivo winked at Sofia (only once).</item>
    </tier>
  </igt>
  <igt id="igt3315-15" doc-id="3315" line-range="327-330" tag-types="M+CN L G T">
    <metadata>
      <meta id="meta1">
        <dc:subject olac:code="srp:hrv" xsi:type="olac:language">Serbocroatian</dc:subject>
        <dc:language olac:code="en" xsi:type="olac:language">English</dc:language>
      </meta>
    </metadata>
    <tier id="r" type="odin" state="raw">
      <item id="r1" line="327" tag="M+CN">  ?habitual;</item>
      <item id="r2" line="328" tag="L">  10)      Mama vodi Ivu u skolu svaki dan.</item>
      <item id="r3" line="329" tag="G">           Mum takes I.    to school every day</item>
      <item id="r4" line="330" tag="T">           `Mum takes Ivo to school every day.'</item>
    </tier>
    <tier id="c" type="odin" alignment="r" state="cleaned">
      <item id="c1" alignment="r1" line="327" tag="M+CN">?habitual;</item>
      <item id="c2" alignment="r2" line="328" tag="L">10)      Mama vodi Ivu u skolu svaki dan.</item>
      <item id="c3" alignment="r3" line="329" tag="G">         Mum takes I.    to school every day</item>
      <item id="c4" alignment="r4" line="330" tag="T">         `Mum takes Ivo to school every day.'</item>
    </tier>
    <tier id="n" type="odin" alignment="c" state="normalized">
      <item id="n1" alignment="c1" line="327" tag="M+CN">?habitual;</item>
      <item id="n2" alignment="c2" line="328" tag="L">Mama vodi Ivu u skolu svaki dan.</item>
      <item id="n3" alignment="c3" line="329" tag="G">Mum takes I.to school every day</item>
      <item id="n4" alignment="c4" line="330" tag="T">Mum takes Ivo to school every day.</item>
    </tier>
  </igt>
  <igt id="igt3315-16" doc-id="3315" line-range="333-336" tag-types="M+CN L G T">
    <metadata>
      <meta id="meta1">
        <dc:subject olac:code="srp:hrv" xsi:type="olac:language">Serbocroatian</dc:subject>
        <dc:language olac:code="en" xsi:type="olac:language">English</dc:language>
      </meta>
    </metadata>
    <tier id="r" type="odin" state="raw">
      <item id="r1" line="333" tag="M+CN">  ?progressive;</item>
      <item id="r2" line="334" tag="L">  11)      Vidim da mama vodi Ivu u skolu.</item>
      <item id="r3" line="335" tag="G">           (I) see that Mum takes I.   to school</item>
      <item id="r4" line="336" tag="T">           `I can see that Mum is taking Ivo to school.'</item>
    </tier>
    <tier id="c" type="odin" alignment="r" state="cleaned">
      <item id="c1" alignment="r1" line="333" tag="M+CN">?progressive;</item>
      <item id="c2" alignment="r2" line="334" tag="L">11)      Vidim da mama vodi Ivu u skolu.</item>
      <item id="c3" alignment="r3" line="335" tag="G">         (I) see that Mum takes I.   to school</item>
      <item id="c4" alignment="r4" line="336" tag="T">         `I can see that Mum is taking Ivo to school.'</item>
    </tier>
    <tier id="n" type="odin" alignment="c" state="normalized">
      <item id="n1" alignment="c1" line="333" tag="M+CN">?progressive;</item>
      <item id="n2" alignment="c2" line="334" tag="L">Vidim da mama vodi Ivu u skolu.</item>
      <item id="n3" alignment="c3" line="335" tag="G">(I) see that Mum takes I.to school</item>
      <item id="n4" alignment="c4" line="336" tag="T">I can see that Mum is taking Ivo to school.</item>
    </tier>
  </igt>
  <igt id="igt3315-17" doc-id="3315" line-range="367-369" tag-types="L+CN G T">
    <metadata>
      <meta id="meta1">
        <dc:subject olac:code="srp:hrv" xsi:type="olac:language">Serbocroatian</dc:subject>
        <dc:language olac:code="en" xsi:type="olac:language">English</dc:language>
      </meta>
    </metadata>
    <tier id="r" type="odin" state="raw">
      <item id="r1" line="367" tag="L+CN">  12)                  a.                imperfective: Ivo je pisao pismo.</item>
      <item id="r2" line="368" tag="G">                                                       I. is write letter</item>
      <item id="r3" line="369" tag="T">                                                       `Ivo was writing a letter.'</item>
    </tier>
    <tier id="c" type="odin" alignment="r" state="cleaned">
      <item id="c1" alignment="r1" line="367" tag="L+CN">12)                  a.                imperfective: Ivo je pisao pismo.</item>
      <item id="c2" alignment="r2" line="368" tag="G">                                                     I. is write letter</item>
      <item id="c3" alignment="r3" line="369" tag="T">                                                     `Ivo was writing a letter.'</item>
    </tier>
    <tier id="n" type="odin" alignment="c" state="normalized">
      <item id="n1" alignment="c1" line="367" tag="L+CN">imperfective: Ivo je pisao pismo.</item>
      <item id="n2" alignment="c2" line="368" tag="G">              I.is write letter</item>
      <item id="n3" alignment="c3" line="369" tag="T">Ivo was writing a letter.</item>
    </tier>
  </igt>
  <igt id="igt3315-18" doc-id="3315" line-range="372-374" tag-types="L+CN G T">
    <metadata>
      <meta id="meta1">
        <dc:subject olac:code="srp:hrv" xsi:type="olac:language">Serbocroatian</dc:subject>
        <dc:language olac:code="en" xsi:type="olac:language">English</dc:language>
      </meta>
    </metadata>
    <tier id="r" type="odin" state="raw">
      <item id="r1" line="372" tag="L+CN">                       b.                perfective:   Ivo je napisao pismo.</item>
      <item id="r2" line="373" tag="G">                                                       I. is write    letter</item>
      <item id="r3" line="374" tag="T">                                                       `Ivo wrote a letter.'</item>
    </tier>
    <tier id="c" type="odin" alignment="r" state="cleaned">
      <item id="c1" alignment="r1" line="372" tag="L+CN">b.                perfective:   Ivo je napisao pismo.</item>
      <item id="c2" alignment="r2" line="373" tag="G">                                I. is write    letter</item>
      <item id="c3" alignment="r3" line="374" tag="T">                                `Ivo wrote a letter.'</item>
    </tier>
    <tier id="n" type="odin" alignment="c" state="normalized">
      <item id="n1" alignment="c1" line="372" tag="L+CN">perfective:   Ivo je napisao pismo.</item>
      <item id="n2" alignment="c2" line="373" tag="G">              I.is write    letter</item>
      <item id="n3" alignment="c3" line="374" tag="T">Ivo wrote a letter.</item>
    </tier>
  </igt>
  <igt id="igt3315-19" doc-id="3315" line-range="508-510" tag-types="L+DB G+DB T+DB">
    <metadata>
      <meta id="meta1">
        <dc:subject olac:code="srp:hrv" xsi:type="olac:language">Serbocroatian</dc:subject>
        <dc:language olac:code="en" xsi:type="olac:language">English</dc:language>
      </meta>
    </metadata>
    <tier id="r" type="odin" state="raw">
      <item id="r1" line="508" tag="L+DB">  15)      a.       *Popijemo       vino.                 b.     *Sutra        odem             na put.</item>
      <item id="r2" line="509" tag="G+DB">                    (we)drinkPf wine                             tomorrow (I)go awayPf on trip</item>
      <item id="r3" line="510" tag="T+DB">                    `We are drinking wine.'                      'I am going away on a trip tomorrow.'</item>
    </tier>
    <tier id="c" type="odin" alignment="r" state="cleaned">
      <item id="c1" alignment="r1" line="508" tag="L+DB">15)      a.       *Popijemo       vino.                 b.     *Sutra        odem             na put.</item>
      <item id="c2" alignment="r2" line="509" tag="G+DB">                  (we)drinkPf wine                             tomorrow (I)go awayPf on trip</item>
      <item id="c3" alignment="r3" line="510" tag="T+DB">                  `We are drinking wine.'                      'I am going away on a trip tomorrow.'</item>
    </tier>
    <tier id="n" type="odin" alignment="c" state="normalized">
      <item id="n1" alignment="c1" judgment="*" line="508" tag="L+DB">Popijemo       vino.                 b.     *Sutra        odem             na put.</item>
      <item id="n2" alignment="c2" line="509" tag="G+DB">(we)drinkPf wine                             tomorrow (I)go awayPf on trip</item>
      <item id="n3" alignment="c3" line="510" tag="T+DB">We are drinking wine.'                      'I am going away on a trip tomorrow.</item>
    </tier>
  </igt>
  <igt id="igt3315-20" doc-id="3315" line-range="578-581" tag-types="L+CR L+CR G T">
    <metadata>
      <meta id="meta1">
        <dc:subject olac:code="srp:hrv" xsi:type="olac:language">Serbocroatian</dc:subject>
        <dc:language olac:code="en" xsi:type="olac:language">English</dc:language>
      </meta>
    </metadata>
    <tier id="r" type="odin" state="raw">
      <item id="r1" line="578" tag="L+CR">                                                                       odobrila prodaju nezdrave hrane.</item>
      <item id="r2" line="579" tag="L+CR">  18)     a.       Vlada          je ju6b `Y 6a `Y XW TV TU TS R</item>
      <item id="r3" line="580" tag="G">                   government is yesterday/today approved sale                          unhealthy food</item>
      <item id="r4" line="581" tag="T">                   `The government approved the sale of unhealthy food yesterday/today.'</item>
    </tier>
    <tier id="c" type="odin" alignment="r" state="cleaned">
      <item id="c1" alignment="r1" line="578 579" tag="L">18)     a.       Vlada          je ju6b `Y 6a `Y XW TV TU TS R       odobrila prodaju nezdrave hrane.</item>
      <item id="c2" alignment="r3" line="580" tag="G">                 government is yesterday/today approved sale                          unhealthy food</item>
      <item id="c3" alignment="r4" line="581" tag="T">                 `The government approved the sale of unhealthy food yesterday/today.'</item>
    </tier>
    <tier id="n" type="odin" alignment="c" state="normalized">
      <item id="n1" alignment="c1" line="578 579" tag="L">Vlada          je ju6b `Y 6a `Y XW TV TU TS R       odobrila prodaju nezdrave hrane.</item>
      <item id="n2" alignment="c2" line="580" tag="G">government is yesterday/today approved sale                          unhealthy food</item>
      <item id="n3" alignment="c3" line="581" tag="T">The government approved the sale of unhealthy food yesterday/today.</item>
    </tier>
  </igt>
  <igt id="igt3315-21" doc-id="3315" line-range="584-586" tag-types="L G T">
    <metadata>
      <meta id="meta1">
        <dc:subject olac:code="srp:hrv" xsi:type="olac:language">Serbocroatian</dc:subject>
        <dc:language olac:code="en" xsi:type="olac:language">English</dc:language>
      </meta>
    </metadata>
    <tier id="r" type="odin" state="raw">
      <item id="r1" line="584" tag="L">          b.       *Vlada          je sutra                        odobrila prodaju nezdrave hrane.</item>
      <item id="r2" line="585" tag="G">                   government is tomorrow approved sale                          unhealthy food</item>
      <item id="r3" line="586" tag="T">                   `The government approved the sale of unhealthy food tomorrow.'</item>
    </tier>
    <tier id="c" type="odin" alignment="r" state="cleaned">
      <item id="c1" alignment="r1" line="584" tag="L">b.       *Vlada          je sutra                        odobrila prodaju nezdrave hrane.</item>
      <item id="c2" alignment="r2" line="585" tag="G">         government is tomorrow approved sale                          unhealthy food</item>
      <item id="c3" alignment="r3" line="586" tag="T">         `The government approved the sale of unhealthy food tomorrow.'</item>
    </tier>
    <tier id="n" type="odin" alignment="c" state="normalized">
      <item id="n1" alignment="c1" judgment="*" line="584" tag="L">Vlada          je sutra                        odobrila prodaju nezdrave hrane.</item>
      <item id="n2" alignment="c2" line="585" tag="G">government is tomorrow approved sale                          unhealthy food</item>
      <item id="n3" alignment="c3" line="586" tag="T">The government approved the sale of unhealthy food tomorrow.</item>
    </tier>
  </igt>
  <igt id="igt3315-22" doc-id="3315" line-range="643-646" tag-types="L+DB+CR+SY L+DB+CR+SY G+DB+SY T+DB+SY">
    <metadata>
      <meta id="meta1">
        <dc:subject olac:code="srp:hrv" xsi:type="olac:language">Serbocroatian</dc:subject>
        <dc:language olac:code="en" xsi:type="olac:language">English</dc:language>
      </meta>
    </metadata>
    <tier id="r" type="odin" state="raw">
      <item id="r1" line="643" tag="L+DB+CR+SY">                                                                                   .             Napusta     sastanak                   .</item>
      <item id="r2" line="644" tag="L+DB+CR+SY">  19)                a.               Napustio je sastanak       T ` x ` yx `w v                                          T `  ` y `</item>
      <item id="r3" line="645" tag="G+DB+SY">                                      (he)left    is meeting swearing                            (he)leaves meeting swearing</item>
      <item id="r4" line="646" tag="T+DB+SY">                                      `He left the meeting swearing.'                            `He is leaving the meeting swearing.'</item>
    </tier>
    <tier id="c" type="odin" alignment="r" state="cleaned">
      <item id="c1" alignment="r1" line="643 644" tag="L+DB+SY">19)                a.               Napustio je sastanak       T ` x ` yx `w v   .             Napusta     sastanak     T `  ` y `    .</item>
      <item id="c2" alignment="r3" line="645" tag="G+DB+SY">                                    (he)left    is meeting swearing                            (he)leaves meeting swearing</item>
      <item id="c3" alignment="r4" line="646" tag="T+DB+SY">                                    `He left the meeting swearing.'                            `He is leaving the meeting swearing.'</item>
    </tier>
    <tier id="n" type="odin" alignment="c" state="normalized">
      <item id="n1" alignment="c1" line="643 644" tag="L+DB+SY">Napustio je sastanak       T ` x ` yx `w v   .             Napusta     sastanak     T `  ` y `    .</item>
      <item id="n2" alignment="c2" line="645" tag="G+DB+SY">(he)left    is meeting swearing                            (he)leaves meeting swearing</item>
      <item id="n3" alignment="c3" line="646" tag="T+DB+SY">He left the meeting swearing.'                            `He is leaving the meeting swearing.</item>
    </tier>
  </igt>
  <igt id="igt3315-23" doc-id="3315" line-range="649-652" tag-types="L G T+DB+SY C">
    <metadata>
      <meta id="meta1">
        <dc:subject olac:code="srp:hrv" xsi:type="olac:language">Serbocroatian</dc:subject>
        <dc:language olac:code="en" xsi:type="olac:language">English</dc:language>
      </meta>
    </metadata>
    <tier id="r" type="odin" state="raw">
      <item id="r1" line="649" tag="L">                     b.               Poljubivsi Mariju, Ivan je napustio sastanak.                Poljubivsi Mariju, Ivan napusta sastanak.</item>
      <item id="r2" line="650" tag="G">                                      kissed      M.       I.   is left                meeting    kissed     M.      I.     leaving meeting</item>
      <item id="r3" line="651" tag="T+DB+SY">                                      `Having kissed Maria, Ivan left the meeting.'/`Having kissed Maria, Ivan is leaving the</item>
      <item id="r4" line="652" tag="C">                                      meeting.'</item>
    </tier>
    <tier id="c" type="odin" alignment="r" state="cleaned">
      <item id="c1" alignment="r1" line="649" tag="L">b.               Poljubivsi Mariju, Ivan je napustio sastanak.                Poljubivsi Mariju, Ivan napusta sastanak.</item>
      <item id="c2" alignment="r2" line="650" tag="G">                 kissed      M.       I.   is left                meeting    kissed     M.      I.     leaving meeting</item>
      <item id="c3" alignment="r3" line="651" tag="T+DB+SY">                 `Having kissed Maria, Ivan left the meeting.'/`Having kissed Maria, Ivan is leaving the</item>
      <item id="c4" alignment="r4" line="652" tag="C">                 meeting.'</item>
    </tier>
    <tier id="n" type="odin" alignment="c" state="normalized">
      <item id="n1" alignment="c1" line="649" tag="L">Poljubivsi Mariju, Ivan je napustio sastanak.                Poljubivsi Mariju, Ivan napusta sastanak.</item>
      <item id="n2" alignment="c2" line="650" tag="G">kissed      M.I.   is left                meeting    kissed     M.I.     leaving meeting</item>
      <item id="n3" alignment="c3" line="651 652" tag="T+DB+SY">Having kissed Maria, Ivan left the meeting.</item>
      <item id="n4" alignment="c3" line="651 652" tag="T+DB+SY+AL">Having kissed Maria, Ivan is leaving the meeting.</item>
    </tier>
  </igt>
  <igt id="igt3315-24" doc-id="3315" line-range="709-711" tag-types="L+DB G+DB T+DB">
    <metadata>
      <meta id="meta1">
        <dc:subject olac:code="srp:hrv" xsi:type="olac:language">Serbocroatian</dc:subject>
        <dc:language olac:code="en" xsi:type="olac:language">English</dc:language>
      </meta>
    </metadata>
    <tier id="r" type="odin" state="raw">
      <item id="r1" line="709" tag="L+DB">  20)                a.               Ljubi          li nju?                                 b.   *Poljubio         li je nju?</item>
      <item id="r2" line="710" tag="G+DB">                                      kisses.Impf Q her                                           (he)kissed.Pf Q is her</item>
      <item id="r3" line="711" tag="T+DB">                                      `Does s/he kiss her?/ Is s/he kissing her?'                 `Has he kissed her?/ Did he kiss her?'</item>
    </tier>
    <tier id="c" type="odin" alignment="r" state="cleaned">
      <item id="c1" alignment="r1" line="709" tag="L+DB">20)                a.               Ljubi          li nju?                                 b.   *Poljubio         li je nju?</item>
      <item id="c2" alignment="r2" line="710" tag="G+DB">                                    kisses.Impf Q her                                           (he)kissed.Pf Q is her</item>
      <item id="c3" alignment="r3" line="711" tag="T+DB">                                    `Does s/he kiss her?/ Is s/he kissing her?'                 `Has he kissed her?/ Did he kiss her?'</item>
    </tier>
    <tier id="n" type="odin" alignment="c" state="normalized">
      <item id="n1" alignment="c1" line="709" tag="L+DB">Ljubi          li nju?                                 b.   *Poljubio         li je nju?</item>
      <item id="n2" alignment="c2" line="710" tag="G+DB">kisses.Impf Q her                                           (he)kissed.Pf Q is her</item>
      <item id="n3" alignment="c3" line="711" tag="T+DB">Does s/he kiss her?/ Is s/he kissing her?'                 `Has he kissed her?/ Did he kiss her?</item>
    </tier>
  </igt>
  <igt id="igt3315-25" doc-id="3315" line-range="715-717" tag-types="L G T">
    <metadata>
      <meta id="meta1">
        <dc:subject olac:code="srp:hrv" xsi:type="olac:language">Serbocroatian</dc:subject>
        <dc:language olac:code="en" xsi:type="olac:language">English</dc:language>
      </meta>
    </metadata>
    <tier id="r" type="odin" state="raw">
      <item id="r1" line="715" tag="L">                     c.               *Poljubi       li nju?</item>
      <item id="r2" line="716" tag="G">                                      (he)kiss.Pf Q her</item>
      <item id="r3" line="717" tag="T">                                      `Does s/he kiss her?/Is s/he kissing her?'</item>
    </tier>
    <tier id="c" type="odin" alignment="r" state="cleaned">
      <item id="c1" alignment="r1" line="715" tag="L">c.               *Poljubi       li nju?</item>
      <item id="c2" alignment="r2" line="716" tag="G">                 (he)kiss.Pf Q her</item>
      <item id="c3" alignment="r3" line="717" tag="T">                 `Does s/he kiss her?/Is s/he kissing her?'</item>
    </tier>
    <tier id="n" type="odin" alignment="c" state="normalized">
      <item id="n1" alignment="c1" judgment="*" line="715" tag="L">Poljubi       li nju?</item>
      <item id="n2" alignment="c2" line="716" tag="G">(he)kiss.Pf Q her</item>
      <item id="n3" alignment="c3" line="717" tag="T">Does s/he kiss her?/Is s/he kissing her?</item>
    </tier>
  </igt>
  <igt id="igt3315-26" doc-id="3315" line-range="942-944" tag-types="L G T+DB">
    <metadata>
      <meta id="meta1">
        <dc:subject olac:code="srp:hrv" xsi:type="olac:language">Serbocroatian</dc:subject>
        <dc:language olac:code="en" xsi:type="olac:language">English</dc:language>
      </meta>
    </metadata>
    <tier id="r" type="odin" state="raw">
      <item id="r1" line="942" tag="L">             b.      Ivo je polako ustao/            ustajao.</item>
      <item id="r2" line="943" tag="G">                     I.           is slowly got up.Pf/Impf.</item>
      <item id="r3" line="944" tag="T+DB">                     `Ivo slowly got up/Ivo was slowly getting up.'</item>
    </tier>
    <tier id="c" type="odin" alignment="r" state="cleaned">
      <item id="c1" alignment="r1" line="942" tag="L">b.      Ivo je polako ustao/            ustajao.</item>
      <item id="c2" alignment="r2" line="943" tag="G">        I.           is slowly got up.Pf/Impf.</item>
      <item id="c3" alignment="r3" line="944" tag="T+DB">        `Ivo slowly got up/Ivo was slowly getting up.'</item>
    </tier>
    <tier id="n" type="odin" alignment="c" state="normalized">
      <item id="n1" alignment="c1" line="942" tag="L">Ivo je polako ustao/            ustajao.</item>
      <item id="n2" alignment="c2" line="943" tag="G">I.is slowly got up.Pf/Impf.</item>
      <item id="n3" alignment="c3" line="944" tag="T+DB">Ivo slowly got up/Ivo was slowly getting up.</item>
    </tier>
  </igt>
  <igt id="igt3315-27" doc-id="3315" line-range="947-950" tag-types="L+CR L+CR G T+DB">
    <metadata>
      <meta id="meta1">
        <dc:subject olac:code="srp:hrv" xsi:type="olac:language">Serbocroatian</dc:subject>
        <dc:language olac:code="en" xsi:type="olac:language">English</dc:language>
      </meta>
    </metadata>
    <tier id="r" type="odin" state="raw">
      <item id="r1" line="947" tag="L+CR">                                      su poispijale/ ispijale                       jednu po jednu.</item>
      <item id="r2" line="948" tag="L+CR">             c.      6?T?ÇÆ ?                                y?T?T??</item>
      <item id="r3" line="949" tag="G">                     women are drink.PfIter/ImpfIter glasses one by one</item>
      <item id="r4" line="950" tag="T+DB">                     `Women drank glasses one by one/Women were drinking glasses one by one.'</item>
    </tier>
    <tier id="c" type="odin" alignment="r" state="cleaned">
      <item id="c1" alignment="r1" line="947 948" tag="L">c.      6?T?ÇÆ ?       su poispijale/ ispijale  y?T?T??              jednu po jednu.</item>
      <item id="c2" alignment="r3" line="949" tag="G">        women are drink.PfIter/ImpfIter glasses one by one</item>
      <item id="c3" alignment="r4" line="950" tag="T+DB">        `Women drank glasses one by one/Women were drinking glasses one by one.'</item>
    </tier>
    <tier id="n" type="odin" alignment="c" state="normalized">
      <item id="n1" alignment="c1" line="947 948" tag="L">6?T?ÇÆ ?       su poispijale/ ispijale  y?T?T??              jednu po jednu.</item>
      <item id="n2" alignment="c2" line="949" tag="G">women are drink.PfIter/ImpfIter glasses one by one</item>
      <item id="n3" alignment="c3" line="950" tag="T+DB">Women drank glasses one by one/Women were drinking glasses one by one.</item>
    </tier>
  </igt>
</xigt-corpus>
