<xigt-corpus xmlns:dc="http://purl.org/dc/elements/1.1/" xmlns:olac="http://www.language-archives.org/OLAC/1.1/" xmlns:xsi="http://www.w3.org/2001/XMLSchema-instance">
  <igt id="igt3908-1" doc-id="3908" line-range="93-97" tag-types="M+CN L G T T+LT+AL">
    <metadata>
      <meta id="meta1">
        <dc:subject olac:code="cmn" xsi:type="olac:language">Mandarin Chinese</dc:subject>
        <dc:language olac:code="en" xsi:type="olac:language">English</dc:language>
      </meta>
    </metadata>
    <tier id="r" type="odin" state="raw">
      <item id="r1" line="93" tag="M+CN">  (3) a. Adversive passive (older):</item>
      <item id="r2" line="94" tag="L">         ta bei         (gongsi) chezi-le</item>
      <item id="r3" line="95" tag="G">         s/he suffer (co mpany) fire-PERF</item>
      <item id="r4" line="96" tag="T">         'S/he was fired (by the company)'</item>
      <item id="r5" line="97" tag="T+LT+AL">          (lit.: 'S/he suffered (when) the company fired her')</item>
    </tier>
    <tier id="c" type="odin" alignment="r" state="cleaned">
      <item id="c1" alignment="r1" line="93" tag="M+CN">(3) a. Adversive passive (older):</item>
      <item id="c2" alignment="r2" line="94" tag="L">ta bei         (gongsi) chezi-le</item>
      <item id="c3" alignment="r3" line="95" tag="G">s/he suffer (co mpany) fire-PERF</item>
      <item id="c4" alignment="r4" line="96" tag="T">'S/he was fired (by the company)'</item>
      <item id="c5" alignment="r5" line="97" tag="T+LT+AL"> (lit.: 'S/he suffered (when) the company fired her')</item>
    </tier>
    <tier id="n" type="odin" alignment="c" state="normalized">
      <item id="n1" alignment="c1" line="93" tag="M+CN">(3) a. Adversive passive (older):</item>
      <item id="n2" alignment="c2" line="94" tag="L">ta bei         (gongsi) chezi-le</item>
      <item id="n3" alignment="c3" line="95" tag="G">s/he suffer (co mpany) fire-PERF</item>
      <item id="n4" alignment="c4" line="96" tag="T">S/he was fired (by the company)</item>
      <item id="n5" alignment="c5" line="97" tag="M">(lit.: 'S/he suffered (when) the company fired her')</item>
    </tier>
  </igt>
  <igt id="igt3908-2" doc-id="3908" line-range="99-103" tag-types="M+CN L G T T+LT+AL">
    <metadata>
      <meta id="meta1">
        <dc:subject olac:code="cmn" xsi:type="olac:language">Mandarin Chinese</dc:subject>
        <dc:language olac:code="en" xsi:type="olac:language">English</dc:language>
      </meta>
    </metadata>
    <tier id="r" type="odin" state="raw">
      <item id="r1" line="99" tag="M+CN">      b. Generalized passive (newer):</item>
      <item id="r2" line="100" tag="L">         sheng-cheng         bei      jiefang-le</item>
      <item id="r3" line="101" tag="G">         province-capital PASS liberate-PERF</item>
      <item id="r4" line="102" tag="T">         'the provincial capital was liber ated'</item>
      <item id="r5" line="103" tag="T+LT+AL">         (lit.: 'the provincial capital suffered (when someone) liberated it')</item>
    </tier>
    <tier id="c" type="odin" alignment="r" state="cleaned">
      <item id="c1" alignment="r1" line="99" tag="M+CN">b. Generalized passive (newer):</item>
      <item id="c2" alignment="r2" line="100" tag="L">sheng-cheng         bei      jiefang-le</item>
      <item id="c3" alignment="r3" line="101" tag="G">province-capital PASS liberate-PERF</item>
      <item id="c4" alignment="r4" line="102" tag="T">'the provincial capital was liber ated'</item>
      <item id="c5" alignment="r5" line="103" tag="T+LT+AL">(lit.: 'the provincial capital suffered (when someone) liberated it')</item>
    </tier>
    <tier id="n" type="odin" alignment="c" state="normalized">
      <item id="n1" alignment="c1" line="99" tag="M+CN">b. Generalized passive (newer):</item>
      <item id="n2" alignment="c2" line="100" tag="L">sheng-cheng         bei      jiefang-le</item>
      <item id="n3" alignment="c3" line="101" tag="G">province-capital PASS liberate-PERF</item>
      <item id="n4" alignment="c4" line="102" tag="T">the provincial capital was liber ated</item>
      <item id="n5" alignment="c5" line="103" tag="M">(lit.: 'the provincial capital suffered (when someone) liberated it')</item>
    </tier>
  </igt>
  <igt id="igt3908-3" doc-id="3908" line-range="117-120" tag-types="M+CN L G T">
    <metadata>
      <meta id="meta1">
        <dc:subject olac:code="ute" xsi:type="olac:language">Ute</dc:subject>
        <dc:language olac:code="en" xsi:type="olac:language">English</dc:language>
      </meta>
    </metadata>
    <tier id="r" type="odin" state="raw">
      <item id="r1" line="117" tag="M+CN">  (4) a. Passive:</item>
      <item id="r2" line="118" tag="L">         múusa-chi paxá-ta-pu,=ga</item>
      <item id="r3" line="119" tag="G">         cat-OBJ kill-PASS-REM</item>
      <item id="r4" line="120" tag="T">         'The cat was killed'</item>
    </tier>
    <tier id="c" type="odin" alignment="r" state="cleaned">
      <item id="c1" alignment="r1" line="117" tag="M+CN">(4) a. Passive:</item>
      <item id="c2" alignment="r2" line="118" tag="L">múusa-chi paxá-ta-pu,=ga</item>
      <item id="c3" alignment="r3" line="119" tag="G">cat-OBJ kill-PASS-REM</item>
      <item id="c4" alignment="r4" line="120" tag="T">'The cat was killed'</item>
    </tier>
    <tier id="n" type="odin" alignment="c" state="normalized">
      <item id="n1" alignment="c1" line="117" tag="M+CN">(4) a. Passive:</item>
      <item id="n2" alignment="c2" line="118" tag="L">múusa-chi paxá-ta-pu,=ga</item>
      <item id="n3" alignment="c3" line="119" tag="G">cat-OBJ kill-PASS-REM</item>
      <item id="n4" alignment="c4" line="120" tag="T">The cat was killed</item>
    </tier>
  </igt>
  <igt id="igt3908-4" doc-id="3908" line-range="122-125" tag-types="M+CN L G T">
    <metadata>
      <meta id="meta1">
        <dc:subject olac:code="ute" xsi:type="olac:language">Ute</dc:subject>
        <dc:language olac:code="en" xsi:type="olac:language">English</dc:language>
      </meta>
    </metadata>
    <tier id="r" type="odin" state="raw">
      <item id="r1" line="122" tag="M+CN">       b. Verb-phrase nominalization:</item>
      <item id="r2" line="123" tag="L">          múusa-paxá-ta ka-'áy-wa-t     'ura-'ay</item>
      <item id="r3" line="124" tag="G">          cat-kill-NOM NEG-good-NEG-NOM be-IMM</item>
      <item id="r4" line="125" tag="T">          'Cat-killing is bad'</item>
    </tier>
    <tier id="c" type="odin" alignment="r" state="cleaned">
      <item id="c1" alignment="r1" line="122" tag="M+CN">b. Verb-phrase nominalization:</item>
      <item id="c2" alignment="r2" line="123" tag="L">múusa-paxá-ta ka-'áy-wa-t     'ura-'ay</item>
      <item id="c3" alignment="r3" line="124" tag="G">cat-kill-NOM NEG-good-NEG-NOM be-IMM</item>
      <item id="c4" alignment="r4" line="125" tag="T">'Cat-killing is bad'</item>
    </tier>
    <tier id="n" type="odin" alignment="c" state="normalized">
      <item id="n1" alignment="c1" line="122" tag="M+CN">b. Verb-phrase nominalization:</item>
      <item id="n2" alignment="c2" line="123" tag="L">múusa-paxá-ta ka-'áy-wa-t     'ura-'ay</item>
      <item id="n3" alignment="c3" line="124" tag="G">cat-kill-NOM NEG-good-NEG-NOM be-IMM</item>
      <item id="n4" alignment="c4" line="125" tag="T">Cat-killing is bad</item>
    </tier>
  </igt>
  <igt id="igt3908-5" doc-id="3908" line-range="134-138" tag-types="M+CN L G T T+LT">
    <metadata>
      <meta id="meta1">
        <dc:subject olac:code="kmb" xsi:type="olac:language">Kimbundu</dc:subject>
        <dc:language olac:code="en" xsi:type="olac:language">English</dc:language>
      </meta>
    </metadata>
    <tier id="r" type="odin" state="raw">
      <item id="r1" line="134" tag="M+CN">  (5) a. Passive:</item>
      <item id="r2" line="135" tag="L">         Nzua a-mu-mono kwa meme</item>
      <item id="r3" line="136" tag="G">         John they-him-saw by me</item>
      <item id="r4" line="137" tag="T">         'John was seen by me'</item>
      <item id="r5" line="138" tag="T+LT">         (lit.: 'John, they saw him by me')</item>
    </tier>
    <tier id="c" type="odin" alignment="r" state="cleaned">
      <item id="c1" alignment="r1" line="134" tag="M+CN">(5) a. Passive:</item>
      <item id="c2" alignment="r2" line="135" tag="L">Nzua a-mu-mono kwa meme</item>
      <item id="c3" alignment="r3" line="136" tag="G">John they-him-saw by me</item>
      <item id="c4" alignment="r4" line="137" tag="T">'John was seen by me'</item>
      <item id="c5" alignment="r5" line="138" tag="T+LT">(lit.: 'John, they saw him by me')</item>
    </tier>
    <tier id="n" type="odin" alignment="c" state="normalized">
      <item id="n1" alignment="c1" line="134" tag="M+CN">(5) a. Passive:</item>
      <item id="n2" alignment="c2" line="135" tag="L">Nzua a-mu-mono kwa meme</item>
      <item id="n3" alignment="c3" line="136" tag="G">John they-him-saw by me</item>
      <item id="n4" alignment="c4" line="137" tag="T">John was seen by me</item>
      <item id="n5" alignment="c5" line="138" tag="M">(lit.: 'John, they saw him by me')</item>
    </tier>
  </igt>
  <igt id="igt3908-6" doc-id="3908" line-range="140-143" tag-types="M+CN L G T">
    <metadata>
      <meta id="meta1">
        <dc:subject olac:code="kmb" xsi:type="olac:language">Kimbundu</dc:subject>
        <dc:language olac:code="en" xsi:type="olac:language">English</dc:language>
      </meta>
    </metadata>
    <tier id="r" type="odin" state="raw">
      <item id="r1" line="140" tag="M+CN">       b. L-dislocation with full-NP subject:</item>
      <item id="r2" line="141" tag="L">          Nzua, aana      a-mu-mono</item>
      <item id="r3" line="142" tag="G">          John children they-him-saw</item>
      <item id="r4" line="143" tag="T">          'John, the children saw him'</item>
    </tier>
    <tier id="c" type="odin" alignment="r" state="cleaned">
      <item id="c1" alignment="r1" line="140" tag="M+CN">b. L-dislocation with full-NP subject:</item>
      <item id="c2" alignment="r2" line="141" tag="L">Nzua, aana      a-mu-mono</item>
      <item id="c3" alignment="r3" line="142" tag="G">John children they-him-saw</item>
      <item id="c4" alignment="r4" line="143" tag="T">'John, the children saw him'</item>
    </tier>
    <tier id="n" type="odin" alignment="c" state="normalized">
      <item id="n1" alignment="c1" line="140" tag="M+CN">b. L-dislocation with full-NP subject:</item>
      <item id="n2" alignment="c2" line="141" tag="L">Nzua, aana      a-mu-mono</item>
      <item id="n3" alignment="c3" line="142" tag="G">John children they-him-saw</item>
      <item id="n4" alignment="c4" line="143" tag="T">John, the children saw him</item>
    </tier>
  </igt>
  <igt id="igt3908-7" doc-id="3908" line-range="145-149" tag-types="M+CN L G T+EX T+AL+EX">
    <metadata>
      <meta id="meta1">
        <dc:subject olac:code="kmb" xsi:type="olac:language">Kimbundu</dc:subject>
        <dc:language olac:code="en" xsi:type="olac:language">English</dc:language>
      </meta>
    </metadata>
    <tier id="r" type="odin" state="raw">
      <item id="r1" line="145" tag="M+CN">       c. L-dislocation with pronominal subject:</item>
      <item id="r2" line="146" tag="L">          Nzua, a-mu-mono</item>
      <item id="r3" line="147" tag="G">          John they-him-saw</item>
      <item id="r4" line="148" tag="T+EX">           (i) Anaphoric active: 'John, they saw him' (anaphor ic/act ive)</item>
      <item id="r5" line="149" tag="T+AL+EX">           (ii) Impersonal passive: 'John, he was seen' (impersonal/passive)</item>
    </tier>
    <tier id="c" type="odin" alignment="r" state="cleaned">
      <item id="c1" alignment="r1" line="145" tag="M+CN">c. L-dislocation with pronominal subject:</item>
      <item id="c2" alignment="r2" line="146" tag="L">Nzua, a-mu-mono</item>
      <item id="c3" alignment="r3" line="147" tag="G">John they-him-saw</item>
      <item id="c4" alignment="r4" line="148" tag="T+EX"> (i) Anaphoric active: 'John, they saw him' (anaphor ic/act ive)</item>
      <item id="c5" alignment="r5" line="149" tag="T+AL+EX"> (ii) Impersonal passive: 'John, he was seen' (impersonal/passive)</item>
    </tier>
    <tier id="n" type="odin" alignment="c" state="normalized">
      <item id="n1" alignment="c1" line="145" tag="M+CN">c. L-dislocation with pronominal subject:</item>
      <item id="n2" alignment="c2" line="146" tag="L">Nzua, a-mu-mono</item>
      <item id="n3" alignment="c3" line="147" tag="G">John they-him-saw</item>
      <item id="n4" alignment="c4" line="148 149" tag="T+AL+EX">(i) Anaphoric active: 'John, they saw him' (anaphor ic/act ive) (ii) Impersonal passive: 'John, he was seen</item>
      <item id="n5" alignment="c4" line="148 149" tag="M">(impersonal/passive)</item>
    </tier>
  </igt>
  <igt id="igt3908-8" doc-id="3908" line-range="158-161" tag-types="M+CN L G T">
    <metadata>
      <meta id="meta1">
        <dc:subject olac:code="xsr" xsi:type="olac:language">Sherpa</dc:subject>
        <dc:language olac:code="en" xsi:type="olac:language">English</dc:language>
      </meta>
    </metadata>
    <tier id="r" type="odin" state="raw">
      <item id="r1" line="158" tag="M+CN">  (6) a. Non-anaphoric active:</item>
      <item id="r2" line="159" tag="L">         ti   mi-t i-gi       chenyi chaq-sung</item>
      <item id="r3" line="160" tag="G">         DEF man-DEF-ERG cup/ABS break-PAST/EVID</item>
      <item id="r4" line="161" tag="T">         'The man broke the cup'</item>
    </tier>
    <tier id="c" type="odin" alignment="r" state="cleaned">
      <item id="c1" alignment="r1" line="158" tag="M+CN">(6) a. Non-anaphoric active:</item>
      <item id="c2" alignment="r2" line="159" tag="L">ti   mi-t i-gi       chenyi chaq-sung</item>
      <item id="c3" alignment="r3" line="160" tag="G">DEF man-DEF-ERG cup/ABS break-PAST/EVID</item>
      <item id="c4" alignment="r4" line="161" tag="T">'The man broke the cup'</item>
    </tier>
    <tier id="n" type="odin" alignment="c" state="normalized">
      <item id="n1" alignment="c1" line="158" tag="M+CN">(6) a. Non-anaphoric active:</item>
      <item id="n2" alignment="c2" line="159" tag="L">ti   mi-t i-gi       chenyi chaq-sung</item>
      <item id="n3" alignment="c3" line="160" tag="G">DEF man-DEF-ERG cup/ABS break-PAST/EVID</item>
      <item id="n4" alignment="c4" line="161" tag="T">The man broke the cup</item>
    </tier>
  </igt>
  <igt id="igt3908-9" doc-id="3908" line-range="168-173" tag-types="M+CN L G T+EX T+AL+EX T+AL">
    <metadata>
      <meta id="meta1">
        <dc:subject olac:code="xsr" xsi:type="olac:language">Sherpa</dc:subject>
        <dc:language olac:code="en" xsi:type="olac:language">English</dc:language>
      </meta>
    </metadata>
    <tier id="r" type="odin" state="raw">
      <item id="r1" line="168" tag="M+CN">      b. Anaphoric agent:</item>
      <item id="r2" line="169" tag="L">         chenyi     chaq-sung</item>
      <item id="r3" line="170" tag="G">         cup/ABS break-PAST/EVID</item>
      <item id="r4" line="171" tag="T+EX">           (i) Active interpretation: 'He/she broke the cup'</item>
      <item id="r5" line="172" tag="T+AL+EX">           (ii) Passive interpretation: 'The cup was broken',</item>
      <item id="r6" line="173" tag="T+AL">                                         'Someone broke the cup'</item>
    </tier>
    <tier id="c" type="odin" alignment="r" state="cleaned">
      <item id="c1" alignment="r1" line="168" tag="M+CN">b. Anaphoric agent:</item>
      <item id="c2" alignment="r2" line="169" tag="L">chenyi     chaq-sung</item>
      <item id="c3" alignment="r3" line="170" tag="G">cup/ABS break-PAST/EVID</item>
      <item id="c4" alignment="r4" line="171" tag="T+EX">  (i) Active interpretation: 'He/she broke the cup'</item>
      <item id="c5" alignment="r5" line="172" tag="T+AL+EX">  (ii) Passive interpretation: 'The cup was broken',</item>
      <item id="c6" alignment="r6" line="173" tag="T+AL">                                'Someone broke the cup'</item>
    </tier>
    <tier id="n" type="odin" alignment="c" state="normalized">
      <item id="n1" alignment="c1" line="168" tag="M+CN">b. Anaphoric agent:</item>
      <item id="n2" alignment="c2" line="169" tag="L">chenyi     chaq-sung</item>
      <item id="n3" alignment="c3" line="170" tag="G">cup/ABS break-PAST/EVID</item>
      <item id="n4" alignment="c4" line="171" note="(i) Active interpretation:" tag="T+EX">He/she broke the cup</item>
      <item id="n5" alignment="c5" line="172 173" tag="T+AL+EX">(ii) Passive interpretation: 'The cup was broken', 'Someone broke the cup</item>
    </tier>
  </igt>
  <igt id="igt3908-10" doc-id="3908" line-range="286-290" tag-types="M+CN M+CN L G T">
    <metadata>
      <meta id="meta1">
        <dc:subject olac:code="ute" xsi:type="olac:language">Ute</dc:subject>
        <dc:language olac:code="en" xsi:type="olac:language">English</dc:language>
      </meta>
    </metadata>
    <tier id="r" type="odin" state="raw">
      <item id="r1" line="286" tag="M+CN">  (10) Ute VP-nominalization passive (D):</item>
      <item id="r2" line="287" tag="M+CN">      a. Nominalization:</item>
      <item id="r3" line="288" tag="L">         múusachi paqxa-ta-'u              ka-'ay-wa-t 'ura-pu,-ga</item>
      <item id="r4" line="289" tag="G">         cat/OBJ kill-NOM-3/POSS NEG-good-NEG-NOM be-REM</item>
      <item id="r5" line="290" tag="T">         'His/her killing (of) the cat was bad'</item>
    </tier>
    <tier id="c" type="odin" alignment="r" state="cleaned">
      <item id="c1" alignment="r1" line="286" tag="M+CN">(10) Ute VP-nominalization passive (D):</item>
      <item id="c2" alignment="r2" line="287" tag="M+CN">a. Nominalization:</item>
      <item id="c3" alignment="r3" line="288" tag="L">múusachi paqxa-ta-'u              ka-'ay-wa-t 'ura-pu,-ga</item>
      <item id="c4" alignment="r4" line="289" tag="G">cat/OBJ kill-NOM-3/POSS NEG-good-NEG-NOM be-REM</item>
      <item id="c5" alignment="r5" line="290" tag="T">'His/her killing (of) the cat was bad'</item>
    </tier>
    <tier id="n" type="odin" alignment="c" state="normalized">
      <item id="n1" alignment="c1" line="286" tag="M+CN">(10) Ute VP-nominalization passive (D):</item>
      <item id="n2" alignment="c2" line="287" tag="M+CN">a. Nominalization:</item>
      <item id="n3" alignment="c3" line="288" tag="L">múusachi paqxa-ta-'u              ka-'ay-wa-t 'ura-pu,-ga</item>
      <item id="n4" alignment="c4" line="289" tag="G">cat/OBJ kill-NOM-3/POSS NEG-good-NEG-NOM be-REM</item>
      <item id="n5" alignment="c5" line="290" tag="T">His/her killing (of) the cat was bad</item>
    </tier>
  </igt>
  <igt id="igt3908-11" doc-id="3908" line-range="291-294" tag-types="M+EX L G T">
    <metadata>
      <meta id="meta1">
        <dc:subject olac:code="ute" xsi:type="olac:language">Ute</dc:subject>
        <dc:language olac:code="en" xsi:type="olac:language">English</dc:language>
      </meta>
    </metadata>
    <tier id="r" type="odin" state="raw">
      <item id="r1" line="291" tag="M+EX">      a. Passive:</item>
      <item id="r2" line="292" tag="L">        múusachi paqxa-ta-pu,-gay-'u</item>
      <item id="r3" line="293" tag="G">        cat/OBJ kill-PASS-REM-3/OBJ</item>
      <item id="r4" line="294" tag="T">        'The cat was killed'</item>
    </tier>
    <tier id="c" type="odin" alignment="r" state="cleaned">
      <item id="c1" alignment="r1" line="291" tag="M+EX">a. Passive:</item>
      <item id="c2" alignment="r2" line="292" tag="L">múusachi paqxa-ta-pu,-gay-'u</item>
      <item id="c3" alignment="r3" line="293" tag="G">cat/OBJ kill-PASS-REM-3/OBJ</item>
      <item id="c4" alignment="r4" line="294" tag="T">'The cat was killed'</item>
    </tier>
    <tier id="n" type="odin" alignment="c" state="normalized">
      <item id="n1" alignment="c1" line="291" tag="M+EX">a. Passive:</item>
      <item id="n2" alignment="c2" line="292" tag="L">múusachi paqxa-ta-pu,-gay-'u</item>
      <item id="n3" alignment="c3" line="293" tag="G">cat/OBJ kill-PASS-REM-3/OBJ</item>
      <item id="n4" alignment="c4" line="294" tag="T">The cat was killed</item>
    </tier>
  </igt>
  <igt id="igt3908-12" doc-id="3908" line-range="296-302" tag-types="M+EX L G M+EX T M T+AL">
    <metadata>
      <meta id="meta1">
        <dc:subject olac:code="kmb" xsi:type="olac:language">Kimbundu</dc:subject>
        <dc:language olac:code="en" xsi:type="olac:language">English</dc:language>
      </meta>
    </metadata>
    <tier id="r" type="odin" state="raw">
      <item id="r1" line="296" tag="M+EX">  (11) Kimbundu L-dislocation/impersonal 'they' passive (E):</item>
      <item id="r2" line="297" tag="L">       Nzua a-mu-mono</item>
      <item id="r3" line="298" tag="G">       John they-him-saw</item>
      <item id="r4" line="299" tag="M+EX">         a. Active, anaphoric agent:</item>
      <item id="r5" line="300" tag="T">           'John, they saw him'</item>
      <item id="r6" line="301" tag="M">         b. Passive, impersonal agent:</item>
      <item id="r7" line="302" tag="T+AL">            'John was seen'</item>
    </tier>
    <tier id="c" type="odin" alignment="r" state="cleaned">
      <item id="c1" alignment="r1" line="296" tag="M+EX">(11) Kimbundu L-dislocation/impersonal 'they' passive (E):</item>
      <item id="c2" alignment="r2" line="297" tag="L">Nzua a-mu-mono</item>
      <item id="c3" alignment="r3" line="298" tag="G">John they-him-saw</item>
      <item id="c4" alignment="r4" line="299" tag="M+EX">a. Active, anaphoric agent:</item>
      <item id="c5" alignment="r5" line="300" tag="T">    'John, they saw him'</item>
      <item id="c6" alignment="r6" line="301" tag="M">b. Passive, impersonal agent:</item>
      <item id="c7" alignment="r7" line="302" tag="T+AL">     'John was seen'</item>
    </tier>
    <tier id="n" type="odin" alignment="c" state="normalized">
      <item id="n1" alignment="c1" line="296" tag="M+EX">(11) Kimbundu L-dislocation/impersonal 'they' passive (E):</item>
      <item id="n2" alignment="c2" line="297" tag="L">Nzua a-mu-mono</item>
      <item id="n3" alignment="c3" line="298" tag="G">John they-him-saw</item>
      <item id="n4" alignment="c4" line="299" tag="M+EX">a. Active, anaphoric agent:</item>
      <item id="n5" alignment="c5" line="300" tag="T">John, they saw him</item>
      <item id="n6" alignment="c6" line="301" tag="M">b. Passive, impersonal agent:</item>
      <item id="n7" alignment="c7" line="302" tag="T+AL">John was seen</item>
    </tier>
  </igt>
  <igt id="igt3908-13" doc-id="3908" line-range="304-311" tag-types="M+EX L G M+EX T M+EX T+AL T+AL">
    <metadata>
      <meta id="meta1">
        <dc:subject olac:code="xsr" xsi:type="olac:language">Sherpa</dc:subject>
        <dc:language olac:code="en" xsi:type="olac:language">English</dc:language>
      </meta>
    </metadata>
    <tier id="r" type="odin" state="raw">
      <item id="r1" line="304" tag="M+EX">  (12) Sherpa zero-anaphora passive (F):</item>
      <item id="r2" line="305" tag="L">         chenyi chaqx-sung</item>
      <item id="r3" line="306" tag="G">         cup/ABS break-PAST/EVID</item>
      <item id="r4" line="307" tag="M+EX">           a. Active, anaphoric agent:</item>
      <item id="r5" line="308" tag="T">             'he/she broke the cup'</item>
      <item id="r6" line="309" tag="M+EX">           b. Passive, impersonal agent:</item>
      <item id="r7" line="310" tag="T+AL">              'The cup was broken'</item>
      <item id="r8" line="311" tag="T+AL">              'Someone broke the cup'</item>
    </tier>
    <tier id="c" type="odin" alignment="r" state="cleaned">
      <item id="c1" alignment="r1" line="304" tag="M+EX">(12) Sherpa zero-anaphora passive (F):</item>
      <item id="c2" alignment="r2" line="305" tag="L">chenyi chaqx-sung</item>
      <item id="c3" alignment="r3" line="306" tag="G">cup/ABS break-PAST/EVID</item>
      <item id="c4" alignment="r4" line="307" tag="M+EX">a. Active, anaphoric agent:</item>
      <item id="c5" alignment="r5" line="308" tag="T">    'he/she broke the cup'</item>
      <item id="c6" alignment="r6" line="309" tag="M+EX">b. Passive, impersonal agent:</item>
      <item id="c7" alignment="r7" line="310" tag="T+AL">     'The cup was broken'</item>
      <item id="c8" alignment="r8" line="311" tag="T+AL">     'Someone broke the cup'</item>
    </tier>
    <tier id="n" type="odin" alignment="c" state="normalized">
      <item id="n1" alignment="c1" line="304" tag="M+EX">(12) Sherpa zero-anaphora passive (F):</item>
      <item id="n2" alignment="c2" line="305" tag="L">chenyi chaqx-sung</item>
      <item id="n3" alignment="c3" line="306" tag="G">cup/ABS break-PAST/EVID</item>
      <item id="n4" alignment="c4" line="307" tag="M+EX">a. Active, anaphoric agent:</item>
      <item id="n5" alignment="c5" line="308" tag="T">he/she broke the cup</item>
      <item id="n6" alignment="c6" line="309" tag="M+EX">b. Passive, impersonal agent:</item>
      <item id="n7" alignment="c7" line="310" tag="T+AL">The cup was broken</item>
      <item id="n8" alignment="c8" line="311" tag="T+AL">Someone broke the cup</item>
    </tier>
  </igt>
  <igt id="igt3908-14" doc-id="3908" line-range="386-388" tag-types="L G T">
    <metadata>
      <meta id="meta1">
        <dc:subject olac:code="var" xsi:type="olac:language">Guarijío</dc:subject>
        <dc:language olac:code="en" xsi:type="olac:language">English</dc:language>
      </meta>
    </metadata>
    <tier id="r" type="odin" state="raw">
      <item id="r1" line="386" tag="L">  (13) a. Owéru wicho-ré     wakirá</item>
      <item id="r2" line="387" tag="G">          Wo men wash-PFV clot hes</item>
      <item id="r3" line="388" tag="T">           'The women washed the clot hes'</item>
    </tier>
    <tier id="c" type="odin" alignment="r" state="cleaned">
      <item id="c1" alignment="r1" line="386" tag="L">(13) a. Owéru wicho-ré     wakirá</item>
      <item id="c2" alignment="r2" line="387" tag="G">        Wo men wash-PFV clot hes</item>
      <item id="c3" alignment="r3" line="388" tag="T">         'The women washed the clot hes'</item>
    </tier>
    <tier id="n" type="odin" alignment="c" state="normalized">
      <item id="n1" alignment="c1" line="386" tag="L">Owéru wicho-ré     wakirá</item>
      <item id="n2" alignment="c2" line="387" tag="G">Wo men wash-PFV clot hes</item>
      <item id="n3" alignment="c3" line="388" tag="T">The women washed the clot hes</item>
    </tier>
  </igt>
  <igt id="igt3908-15" doc-id="3908" line-range="390-392" tag-types="L G T">
    <metadata>
      <meta id="meta1">
        <dc:subject olac:code="var" xsi:type="olac:language">Guarijío</dc:subject>
        <dc:language olac:code="en" xsi:type="olac:language">English</dc:language>
      </meta>
    </metadata>
    <tier id="r" type="odin" state="raw">
      <item id="r1" line="390" tag="L">         b. wicho-ré-tu        wakirá (owéru-e)</item>
      <item id="r2" line="391" tag="G">            wash-PFV-PASS clot hes (women-INSTR)</item>
      <item id="r3" line="392" tag="T">            'The clot hes were washed (by the women)'</item>
    </tier>
    <tier id="c" type="odin" alignment="r" state="cleaned">
      <item id="c1" alignment="r1" line="390" tag="L">b. wicho-ré-tu        wakirá (owéru-e)</item>
      <item id="c2" alignment="r2" line="391" tag="G">   wash-PFV-PASS clot hes (women-INSTR)</item>
      <item id="c3" alignment="r3" line="392" tag="T">   'The clot hes were washed (by the women)'</item>
    </tier>
    <tier id="n" type="odin" alignment="c" state="normalized">
      <item id="n1" alignment="c1" line="390" tag="L">wicho-ré-tu        wakirá (owéru-e)</item>
      <item id="n2" alignment="c2" line="391" tag="G">wash-PFV-PASS clot hes (women-INSTR)</item>
      <item id="n3" alignment="c3" line="392" tag="T">The clot hes were washed (by the women)</item>
    </tier>
  </igt>
  <igt id="igt3908-16" doc-id="3908" line-range="399-401" tag-types="L G T">
    <metadata>
      <meta id="meta1">
        <dc:subject olac:code="tac" xsi:type="olac:language">Tarahumara</dc:subject>
        <dc:language olac:code="en" xsi:type="olac:language">English</dc:language>
      </meta>
    </metadata>
    <tier id="r" type="odin" state="raw">
      <item id="r1" line="399" tag="L">  (14) a. mué-ka nechí   choná-re</item>
      <item id="r2" line="400" tag="G">          you-ENF me/OBJ hit-PERF</item>
      <item id="r3" line="401" tag="T">           'You hit me'</item>
    </tier>
    <tier id="c" type="odin" alignment="r" state="cleaned">
      <item id="c1" alignment="r1" line="399" tag="L">(14) a. mué-ka nechí   choná-re</item>
      <item id="c2" alignment="r2" line="400" tag="G">        you-ENF me/OBJ hit-PERF</item>
      <item id="c3" alignment="r3" line="401" tag="T">         'You hit me'</item>
    </tier>
    <tier id="n" type="odin" alignment="c" state="normalized">
      <item id="n1" alignment="c1" line="399" tag="L">mué-ka nechí   choná-re</item>
      <item id="n2" alignment="c2" line="400" tag="G">you-ENF me/OBJ hit-PERF</item>
      <item id="n3" alignment="c3" line="401" tag="T">You hit me</item>
    </tier>
  </igt>
  <igt id="igt3908-17" doc-id="3908" line-range="403-405" tag-types="L G T">
    <metadata>
      <meta id="meta1">
        <dc:subject olac:code="tac" xsi:type="olac:language">Tarahumara</dc:subject>
        <dc:language olac:code="en" xsi:type="olac:language">English</dc:language>
      </meta>
    </metadata>
    <tier id="r" type="odin" state="raw">
      <item id="r1" line="403" tag="L">       b. né-ka choná-ru-re</item>
      <item id="r2" line="404" tag="G">           I-ENF hit-PASS-PERF</item>
      <item id="r3" line="405" tag="T">           'I was hit (*by you)'</item>
    </tier>
    <tier id="c" type="odin" alignment="r" state="cleaned">
      <item id="c1" alignment="r1" line="403" tag="L">b. né-ka choná-ru-re</item>
      <item id="c2" alignment="r2" line="404" tag="G">    I-ENF hit-PASS-PERF</item>
      <item id="c3" alignment="r3" line="405" tag="T">    'I was hit (*by you)'</item>
    </tier>
    <tier id="n" type="odin" alignment="c" state="normalized">
      <item id="n1" alignment="c1" line="403" tag="L">né-ka choná-ru-re</item>
      <item id="n2" alignment="c2" line="404" tag="G"> I-ENF hit-PASS-PERF</item>
      <item id="n3" alignment="c3" line="405" tag="T">I was hit (*by you)</item>
    </tier>
  </igt>
  <igt id="igt3908-18" doc-id="3908" line-range="432-435" tag-types="M+CN L G T">
    <metadata>
      <meta id="meta1">
        <dc:subject olac:code="spa" xsi:type="olac:language">Spanish</dc:subject>
        <dc:language olac:code="en" xsi:type="olac:language">English</dc:language>
      </meta>
    </metadata>
    <tier id="r" type="odin" state="raw">
      <item id="r1" line="432" tag="M+CN">  (15) a. Reflexive:</item>
      <item id="r2" line="433" tag="L">        se armó de todas sus armas</item>
      <item id="r3" line="434" tag="G">        REF arm/3s with all his weapons</item>
      <item id="r4" line="435" tag="T">        'he armed himself with all his weapons'</item>
    </tier>
    <tier id="c" type="odin" alignment="r" state="cleaned">
      <item id="c1" alignment="r1" line="432" tag="M+CN">(15) a. Reflexive:</item>
      <item id="c2" alignment="r2" line="433" tag="L">se armó de todas sus armas</item>
      <item id="c3" alignment="r3" line="434" tag="G">REF arm/3s with all his weapons</item>
      <item id="c4" alignment="r4" line="435" tag="T">'he armed himself with all his weapons'</item>
    </tier>
    <tier id="n" type="odin" alignment="c" state="normalized">
      <item id="n1" alignment="c1" line="432" tag="M+CN">(15) a. Reflexive:</item>
      <item id="n2" alignment="c2" line="433" tag="L">se armó de todas sus armas</item>
      <item id="n3" alignment="c3" line="434" tag="G">REF arm/3s with all his weapons</item>
      <item id="n4" alignment="c4" line="435" tag="T">he armed himself with all his weapons</item>
    </tier>
  </igt>
  <igt id="igt3908-19" doc-id="3908" line-range="436-439" tag-types="M+CN L G T">
    <metadata>
      <meta id="meta1">
        <dc:subject olac:code="spa" xsi:type="olac:language">Spanish</dc:subject>
        <dc:language olac:code="en" xsi:type="olac:language">English</dc:language>
      </meta>
    </metadata>
    <tier id="r" type="odin" state="raw">
      <item id="r1" line="436" tag="M+CN">       b. Reciprocal:</item>
      <item id="r2" line="437" tag="L">          donde se combatían</item>
      <item id="r3" line="438" tag="G">          where RECIP fight/IMPF/3p</item>
      <item id="r4" line="439" tag="T">          'where they fought each o ther'</item>
    </tier>
    <tier id="c" type="odin" alignment="r" state="cleaned">
      <item id="c1" alignment="r1" line="436" tag="M+CN">b. Reciprocal:</item>
      <item id="c2" alignment="r2" line="437" tag="L">donde se combatían</item>
      <item id="c3" alignment="r3" line="438" tag="G">where RECIP fight/IMPF/3p</item>
      <item id="c4" alignment="r4" line="439" tag="T">'where they fought each o ther'</item>
    </tier>
    <tier id="n" type="odin" alignment="c" state="normalized">
      <item id="n1" alignment="c1" line="436" tag="M+CN">b. Reciprocal:</item>
      <item id="n2" alignment="c2" line="437" tag="L">donde se combatían</item>
      <item id="n3" alignment="c3" line="438" tag="G">where RECIP fight/IMPF/3p</item>
      <item id="n4" alignment="c4" line="439" tag="T">where they fought each o ther</item>
    </tier>
  </igt>
  <igt id="igt3908-20" doc-id="3908" line-range="446-449" tag-types="L G T+CR+EX T+CR+AL+EX">
    <metadata>
      <meta id="meta1">
        <dc:subject olac:code="spa" xsi:type="olac:language">Spanish</dc:subject>
        <dc:language olac:code="en" xsi:type="olac:language">English</dc:language>
      </meta>
    </metadata>
    <tier id="r" type="odin" state="raw">
      <item id="r1" line="446" tag="L">  (16)   le-vieron       en la calle</item>
      <item id="r2" line="447" tag="G">         3s/OBJ-saw/3p in the street</item>
      <item id="r3" line="448" tag="T+CR+EX">         'They saw him in the street' (anaphor ic)</item>
      <item id="r4" line="449" tag="T+CR+AL+EX">          'He was seen in t he street ' (impersonal-p assive)</item>
    </tier>
    <tier id="c" type="odin" alignment="r" state="cleaned">
      <item id="c1" alignment="r1" line="446" tag="L">(16)   le-vieron       en la calle</item>
      <item id="c2" alignment="r2" line="447" tag="G">       3s/OBJ-saw/3p in the street</item>
      <item id="c3" alignment="r3" line="448" tag="T+CR+EX">       'They saw him in the street' (anaphor ic)</item>
    </tier>
    <tier id="n" type="odin" alignment="c" state="normalized">
      <item id="n1" alignment="c1" line="446" tag="L">le-vieron       en la calle</item>
      <item id="n2" alignment="c2" line="447" tag="G">3s/OBJ-saw/3p in the street</item>
      <item id="n3" alignment="c3" line="448" tag="T+CR+EX">They saw him in the street</item>
      <item id="n4" alignment="c3" line="448" tag="M">(anaphor ic)</item>
    </tier>
  </igt>
  <igt id="igt3908-21" doc-id="3908" line-range="453-456" tag-types="M+CN L G T">
    <metadata>
      <meta id="meta1">
        <dc:subject olac:code="spa" xsi:type="olac:language">Spanish</dc:subject>
        <dc:language olac:code="en" xsi:type="olac:language">English</dc:language>
      </meta>
    </metadata>
    <tier id="r" type="odin" state="raw">
      <item id="r1" line="453" tag="M+CN">  (17) a. Active:</item>
      <item id="r2" line="454" tag="L">          quebraron las ventanas</item>
      <item id="r3" line="455" tag="G">          broke/3p the windows</item>
      <item id="r4" line="456" tag="T">          'they broke the windows'</item>
    </tier>
    <tier id="c" type="odin" alignment="r" state="cleaned">
      <item id="c1" alignment="r1" line="453" tag="M+CN">(17) a. Active:</item>
      <item id="c2" alignment="r2" line="454" tag="L">quebraron las ventanas</item>
      <item id="c3" alignment="r3" line="455" tag="G">broke/3p the windows</item>
      <item id="c4" alignment="r4" line="456" tag="T">'they broke the windows'</item>
    </tier>
    <tier id="n" type="odin" alignment="c" state="normalized">
      <item id="n1" alignment="c1" line="453" tag="M+CN">(17) a. Active:</item>
      <item id="n2" alignment="c2" line="454" tag="L">quebraron las ventanas</item>
      <item id="n3" alignment="c3" line="455" tag="G">broke/3p the windows</item>
      <item id="n4" alignment="c4" line="456" tag="T">they broke the windows</item>
    </tier>
  </igt>
  <igt id="igt3908-22" doc-id="3908" line-range="458-462" tag-types="M+CN L G T+CN+EX T+CN+AL+EX">
    <metadata>
      <meta id="meta1">
        <dc:subject olac:code="spa" xsi:type="olac:language">Spanish</dc:subject>
        <dc:language olac:code="en" xsi:type="olac:language">English</dc:language>
      </meta>
    </metadata>
    <tier id="r" type="odin" state="raw">
      <item id="r1" line="458" tag="M+CN">         b. Middle-voice or impersonal passive:</item>
      <item id="r2" line="459" tag="L">            se-quebraron las ventanas</item>
      <item id="r3" line="460" tag="G">            REFL-broke/3p the windows</item>
      <item id="r4" line="461" tag="T+CN+EX">            'the windows were broken' (passive)</item>
      <item id="r5" line="462" tag="T+CN+AL+EX">            'the windows broke' (middle)</item>
    </tier>
    <tier id="c" type="odin" alignment="r" state="cleaned">
      <item id="c1" alignment="r1" line="458" tag="M+CN">b. Middle-voice or impersonal passive:</item>
      <item id="c2" alignment="r2" line="459" tag="L">se-quebraron las ventanas</item>
      <item id="c3" alignment="r3" line="460" tag="G">REFL-broke/3p the windows</item>
      <item id="c4" alignment="r4" line="461" tag="T+CN+EX">'the windows were broken' (passive)</item>
      <item id="c5" alignment="r5" line="462" tag="T+CN+AL+EX">'the windows broke' (middle)</item>
    </tier>
    <tier id="n" type="odin" alignment="c" state="normalized">
      <item id="n1" alignment="c1" line="458" tag="M+CN">b. Middle-voice or impersonal passive:</item>
      <item id="n2" alignment="c2" line="459" tag="L">se-quebraron las ventanas</item>
      <item id="n3" alignment="c3" line="460" tag="G">REFL-broke/3p the windows</item>
      <item id="n4" alignment="c4" line="461 462" tag="T+AL+EX">the windows were broken</item>
      <item id="n5" alignment="c4" line="461 462" note="(passive)" tag="T+AL+EX">the windows broke</item>
      <item id="n6" alignment="c4" line="461 462" tag="M+CN">(middle)</item>
    </tier>
  </igt>
  <igt id="igt3908-23" doc-id="3908" line-range="468-471" tag-types="M+EX L G T">
    <metadata>
      <meta id="meta1">
        <dc:subject olac:code="spa" xsi:type="olac:language">Spanish</dc:subject>
        <dc:language olac:code="en" xsi:type="olac:language">English</dc:language>
      </meta>
    </metadata>
    <tier id="r" type="odin" state="raw">
      <item id="r1" line="468" tag="M+EX">  (18) a. VO order, active:</item>
      <item id="r2" line="469" tag="L">          curaron        los caballo s</item>
      <item id="r3" line="470" tag="G">          cure/PAST/3p the horses</item>
      <item id="r4" line="471" tag="T">           'They cured the horses'</item>
    </tier>
    <tier id="c" type="odin" alignment="r" state="cleaned">
      <item id="c1" alignment="r1" line="468" tag="M+EX">(18) a. VO order, active:</item>
      <item id="c2" alignment="r2" line="469" tag="L">curaron        los caballo s</item>
      <item id="c3" alignment="r3" line="470" tag="G">cure/PAST/3p the horses</item>
      <item id="c4" alignment="r4" line="471" tag="T"> 'They cured the horses'</item>
    </tier>
    <tier id="n" type="odin" alignment="c" state="normalized">
      <item id="n1" alignment="c1" line="468" tag="M+EX">(18) a. VO order, active:</item>
      <item id="n2" alignment="c2" line="469" tag="L">curaron        los caballo s</item>
      <item id="n3" alignment="c3" line="470" tag="G">cure/PAST/3p the horses</item>
      <item id="n4" alignment="c4" line="471" tag="T">They cured the horses</item>
    </tier>
  </igt>
  <igt id="igt3908-24" doc-id="3908" line-range="472-475" tag-types="M+EX L G T">
    <metadata>
      <meta id="meta1">
        <dc:subject olac:code="spa" xsi:type="olac:language">Spanish</dc:subject>
        <dc:language olac:code="en" xsi:type="olac:language">English</dc:language>
      </meta>
    </metadata>
    <tier id="r" type="odin" state="raw">
      <item id="r1" line="472" tag="M+EX">        b. VS order, middle:</item>
      <item id="r2" line="473" tag="L">           se-curaron     los caballos</item>
      <item id="r3" line="474" tag="G">           REF-cure/PAST/3p the horses</item>
      <item id="r4" line="475" tag="T">           'The horses got well'</item>
    </tier>
    <tier id="c" type="odin" alignment="r" state="cleaned">
      <item id="c1" alignment="r1" line="472" tag="M+EX">b. VS order, middle:</item>
      <item id="c2" alignment="r2" line="473" tag="L">se-curaron     los caballos</item>
      <item id="c3" alignment="r3" line="474" tag="G">REF-cure/PAST/3p the horses</item>
      <item id="c4" alignment="r4" line="475" tag="T">'The horses got well'</item>
    </tier>
    <tier id="n" type="odin" alignment="c" state="normalized">
      <item id="n1" alignment="c1" line="472" tag="M+EX">b. VS order, middle:</item>
      <item id="n2" alignment="c2" line="473" tag="L">se-curaron     los caballos</item>
      <item id="n3" alignment="c3" line="474" tag="G">REF-cure/PAST/3p the horses</item>
      <item id="n4" alignment="c4" line="475" tag="T">The horses got well</item>
    </tier>
  </igt>
  <igt id="igt3908-25" doc-id="3908" line-range="485-487" tag-types="L G T">
    <metadata>
      <meta id="meta1">
        <dc:subject olac:code="spa" xsi:type="olac:language">Spanish</dc:subject>
        <dc:language olac:code="en" xsi:type="olac:language">English</dc:language>
      </meta>
    </metadata>
    <tier id="r" type="odin" state="raw">
      <item id="r1" line="485" tag="L">  (19) a. veremos vuestra mugier</item>
      <item id="r2" line="486" tag="G">          see/FUT/1p your woman</item>
      <item id="r3" line="487" tag="T">          'We will see your wife'</item>
    </tier>
    <tier id="c" type="odin" alignment="r" state="cleaned">
      <item id="c1" alignment="r1" line="485" tag="L">(19) a. veremos vuestra mugier</item>
      <item id="c2" alignment="r2" line="486" tag="G">        see/FUT/1p your woman</item>
      <item id="c3" alignment="r3" line="487" tag="T">        'We will see your wife'</item>
    </tier>
    <tier id="n" type="odin" alignment="c" state="normalized">
      <item id="n1" alignment="c1" line="485" tag="L">veremos vuestra mugier</item>
      <item id="n2" alignment="c2" line="486" tag="G">see/FUT/1p your woman</item>
      <item id="n3" alignment="c3" line="487" tag="T">We will see your wife</item>
    </tier>
  </igt>
  <igt id="igt3908-26" doc-id="3908" line-range="489-491" tag-types="L G T">
    <metadata>
      <meta id="meta1">
        <dc:subject olac:code="spa" xsi:type="olac:language">Spanish</dc:subject>
        <dc:language olac:code="en" xsi:type="olac:language">English</dc:language>
      </meta>
    </metadata>
    <tier id="r" type="odin" state="raw">
      <item id="r1" line="489" tag="L">        b. veré          a    la mugier</item>
      <item id="r2" line="490" tag="G">           see/FUT/1s DAT the woman</item>
      <item id="r3" line="491" tag="T">           'I will see (my) wife'</item>
    </tier>
    <tier id="c" type="odin" alignment="r" state="cleaned">
      <item id="c1" alignment="r1" line="489" tag="L">b. veré          a    la mugier</item>
      <item id="c2" alignment="r2" line="490" tag="G">   see/FUT/1s DAT the woman</item>
      <item id="c3" alignment="r3" line="491" tag="T">   'I will see (my) wife'</item>
    </tier>
    <tier id="n" type="odin" alignment="c" state="normalized">
      <item id="n1" alignment="c1" line="489" tag="L">veré          a    la mugier</item>
      <item id="n2" alignment="c2" line="490" tag="G">see/FUT/1s DAT the woman</item>
      <item id="n3" alignment="c3" line="491" tag="T">I will see (my) wife</item>
    </tier>
  </igt>
  <igt id="igt3908-27" doc-id="3908" line-range="499-503" tag-types="L G T T+AL T+AL">
    <metadata>
      <meta id="meta1">
        <dc:subject olac:code="spa" xsi:type="olac:language">Spanish</dc:subject>
        <dc:language olac:code="en" xsi:type="olac:language">English</dc:language>
      </meta>
    </metadata>
    <tier id="r" type="odin" state="raw">
      <item id="r1" line="499" tag="L">  (20) se-cur-aron             los brujos</item>
      <item id="r2" line="500" tag="G">       REF-cure/PAST-3p        the sorcerers</item>
      <item id="r3" line="501" tag="T">          a. Reflexive: 'The    sorcerers cured themselves'</item>
      <item id="r4" line="502" tag="T+AL">          b. Middle: 'The       sorcerers got well'</item>
      <item id="r5" line="503" tag="T+AL">           c. Passive: 'The    sorcerer were cured'</item>
    </tier>
    <tier id="c" type="odin" alignment="r" state="cleaned">
      <item id="c1" alignment="r1" line="499" tag="L">(20) se-cur-aron             los brujos</item>
      <item id="c2" alignment="r2" line="500" tag="G">     REF-cure/PAST-3p        the sorcerers</item>
      <item id="c3" alignment="r3" line="501" tag="T">        a. Reflexive: 'The    sorcerers cured themselves'</item>
      <item id="c4" alignment="r4" line="502" tag="T+AL">        b. Middle: 'The       sorcerers got well'</item>
      <item id="c5" alignment="r5" line="503" tag="T+AL">         c. Passive: 'The    sorcerer were cured'</item>
    </tier>
    <tier id="n" type="odin" alignment="c" state="normalized">
      <item id="n1" alignment="c1" line="499" tag="L">se-cur-aron             los brujos</item>
      <item id="n2" alignment="c2" line="500" tag="G">REF-cure/PAST-3p        the sorcerers</item>
      <item id="n3" alignment="c3" line="501" note="a. Reflexive:" tag="T">The    sorcerers cured themselves</item>
      <item id="n4" alignment="c4" line="502" note="b. Middle:" tag="T+AL">The       sorcerers got well</item>
      <item id="n5" alignment="c5" line="503" note="c. Passive:" tag="T+AL">The    sorcerer were cured</item>
    </tier>
  </igt>
  <igt id="igt3908-28" doc-id="3908" line-range="509-512" tag-types="M+EX L G T">
    <metadata>
      <meta id="meta1">
        <dc:subject olac:code="spa" xsi:type="olac:language">Spanish</dc:subject>
        <dc:language olac:code="en" xsi:type="olac:language">English</dc:language>
      </meta>
    </metadata>
    <tier id="r" type="odin" state="raw">
      <item id="r1" line="509" tag="M+EX">  (21) a. Impersonal passive:</item>
      <item id="r2" line="510" tag="L">          se-curó      a      los brujos</item>
      <item id="r3" line="511" tag="G">          REF-cure/3s DAT the sorcerer</item>
      <item id="r4" line="512" tag="T">          'Someone cured t he sorcerers'</item>
    </tier>
    <tier id="c" type="odin" alignment="r" state="cleaned">
      <item id="c1" alignment="r1" line="509" tag="M+EX">(21) a. Impersonal passive:</item>
      <item id="c2" alignment="r2" line="510" tag="L">se-curó      a      los brujos</item>
      <item id="c3" alignment="r3" line="511" tag="G">REF-cure/3s DAT the sorcerer</item>
      <item id="c4" alignment="r4" line="512" tag="T">'Someone cured t he sorcerers'</item>
    </tier>
    <tier id="n" type="odin" alignment="c" state="normalized">
      <item id="n1" alignment="c1" line="509" tag="M+EX">(21) a. Impersonal passive:</item>
      <item id="n2" alignment="c2" line="510" tag="L">se-curó      a      los brujos</item>
      <item id="n3" alignment="c3" line="511" tag="G">REF-cure/3s DAT the sorcerer</item>
      <item id="n4" alignment="c4" line="512" tag="T">Someone cured t he sorcerers</item>
    </tier>
  </igt>
  <igt id="igt3908-29" doc-id="3908" line-range="513-517" tag-types="M+EX L G T T+AL">
    <metadata>
      <meta id="meta1">
        <dc:subject olac:code="spa" xsi:type="olac:language">Spanish</dc:subject>
        <dc:language olac:code="en" xsi:type="olac:language">English</dc:language>
      </meta>
    </metadata>
    <tier id="r" type="odin" state="raw">
      <item id="r1" line="513" tag="M+EX">       b. Promotional passive or middle:</item>
      <item id="r2" line="514" tag="L">           se-venden bien los apartamentos</item>
      <item id="r3" line="515" tag="G">           REF-sell/3p well t he apartments</item>
      <item id="r4" line="516" tag="T">           'Apartments sell well'</item>
      <item id="r5" line="517" tag="T+AL">           'Apartments are sold well'</item>
    </tier>
    <tier id="c" type="odin" alignment="r" state="cleaned">
      <item id="c1" alignment="r1" line="513" tag="M+EX">b. Promotional passive or middle:</item>
      <item id="c2" alignment="r2" line="514" tag="L">se-venden bien los apartamentos</item>
      <item id="c3" alignment="r3" line="515" tag="G">REF-sell/3p well t he apartments</item>
      <item id="c4" alignment="r4" line="516" tag="T">'Apartments sell well'</item>
      <item id="c5" alignment="r5" line="517" tag="T+AL">'Apartments are sold well'</item>
    </tier>
    <tier id="n" type="odin" alignment="c" state="normalized">
      <item id="n1" alignment="c1" line="513" tag="M+EX">b. Promotional passive or middle:</item>
      <item id="n2" alignment="c2" line="514" tag="L">se-venden bien los apartamentos</item>
      <item id="n3" alignment="c3" line="515" tag="G">REF-sell/3p well t he apartments</item>
      <item id="n4" alignment="c4" line="516" tag="T">Apartments sell well</item>
      <item id="n5" alignment="c5" line="517" tag="T+AL">Apartments are sold well</item>
    </tier>
  </igt>
  <igt id="igt3908-30" doc-id="3908" line-range="523-526" tag-types="M+EX L G T">
    <metadata>
      <meta id="meta1">
        <dc:subject olac:code="spa" xsi:type="olac:language">Spanish</dc:subject>
        <dc:language olac:code="en" xsi:type="olac:language">English</dc:language>
      </meta>
    </metadata>
    <tier id="r" type="odin" state="raw">
      <item id="r1" line="523" tag="M+EX">  (22) a. Promotional se-passive:</item>
      <item id="r2" line="524" tag="L">          las pirámides se-construyeron      por      esclavos</item>
      <item id="r3" line="525" tag="G">          the pyramids REF-constructed/3p by/wit h slaves</item>
      <item id="r4" line="526" tag="T">          'The pyramids were constructed by/wit h slaves'</item>
    </tier>
    <tier id="c" type="odin" alignment="r" state="cleaned">
      <item id="c1" alignment="r1" line="523" tag="M+EX">(22) a. Promotional se-passive:</item>
      <item id="c2" alignment="r2" line="524" tag="L">las pirámides se-construyeron      por      esclavos</item>
      <item id="c3" alignment="r3" line="525" tag="G">the pyramids REF-constructed/3p by/wit h slaves</item>
      <item id="c4" alignment="r4" line="526" tag="T">'The pyramids were constructed by/wit h slaves'</item>
    </tier>
    <tier id="n" type="odin" alignment="c" state="normalized">
      <item id="n1" alignment="c1" line="523" tag="M+EX">(22) a. Promotional se-passive:</item>
      <item id="n2" alignment="c2" line="524" tag="L">las pirámides se-construyeron      por      esclavos</item>
      <item id="n3" alignment="c3" line="525" tag="G">the pyramids REF-constructed/3p by/wit h slaves</item>
      <item id="n4" alignment="c4" line="526" tag="T">The pyramids were constructed by/wit h slaves</item>
    </tier>
  </igt>
  <igt id="igt3908-31" doc-id="3908" line-range="527-530" tag-types="M+EX L G T">
    <metadata>
      <meta id="meta1">
        <dc:subject olac:code="spa" xsi:type="olac:language">Spanish</dc:subject>
        <dc:language olac:code="en" xsi:type="olac:language">English</dc:language>
      </meta>
    </metadata>
    <tier id="r" type="odin" state="raw">
      <item id="r1" line="527" tag="M+EX">        b. Non-promotional ('impersonal) se-passive:</item>
      <item id="r2" line="528" tag="L">           se-destruyó       a     la nació n por los malos gobernantes</item>
      <item id="r3" line="529" tag="G">           REF-destroyed/3s DAT the nation by the bad rulers</item>
      <item id="r4" line="530" tag="T">           'The nation was destroyed by the bad rulers'</item>
    </tier>
    <tier id="c" type="odin" alignment="r" state="cleaned">
      <item id="c1" alignment="r1" line="527" tag="M+EX">b. Non-promotional ('impersonal) se-passive:</item>
      <item id="c2" alignment="r2" line="528" tag="L">se-destruyó       a     la nació n por los malos gobernantes</item>
      <item id="c3" alignment="r3" line="529" tag="G">REF-destroyed/3s DAT the nation by the bad rulers</item>
      <item id="c4" alignment="r4" line="530" tag="T">'The nation was destroyed by the bad rulers'</item>
    </tier>
    <tier id="n" type="odin" alignment="c" state="normalized">
      <item id="n1" alignment="c1" line="527" tag="M+EX">b. Non-promotional ('impersonal) se-passive:</item>
      <item id="n2" alignment="c2" line="528" tag="L">se-destruyó       a     la nació n por los malos gobernantes</item>
      <item id="n3" alignment="c3" line="529" tag="G">REF-destroyed/3s DAT the nation by the bad rulers</item>
      <item id="n4" alignment="c4" line="530" tag="T">The nation was destroyed by the bad rulers</item>
    </tier>
  </igt>
</xigt-corpus>
